Workbook
Name Mes: Mes!$A$2

Sheet BASE
A1: ANIO_NATURAL_MES | B1: POSICION | C1: DESCRIPCION_POSICION | D1: AREA_FUNCIONAL | E1: SUB_AREA_FUNCIONAL | F1: FUNCION | G1: DESCRIPCION_FUNCION | H1: ID_META_4 | I1: SUBDIV_PERSONAL | J1: SOCIEDAD | K1: NOMBRE_JEFE | L1: OBJETO_DE_IMPUTACION | M1: PERSONA | N1: DESCRIPCION_PERSONA | O1: FLAG_LICENCIA | P1: NACIONALIDAD | Q1: USUARIO_DE_RED | R1: OPERACION_PIVOT | S1: OPERACION_DETALLE | T1: UO | U1: GERENCIA_JEFATURA | V1: WC_BC | W1: SEXO | X1: RANGO_ETARIO | Y1: EDAD | Z1: ANIOS_ANTIGUEDAD | AA1: GRUPO_ANTIGUEDAD | AB1: FUENTE | AC1: HC | AD1: EA | AE1: BUDGET | AF1: ENCUADRE | AG1: CLUSTER | AH1: NO_HC | AI1: CS | AJ1: OL | AK1: FECHA_ANIVERSARIO_SAP
A2: 46266 | B2: 3360828 | C2: O&M Services Director | D2: EFIS | E2: EFIS | G2: =Table1[[#This Row],[DESCRIPCION_POSICION]] -> O&M Services Director | H2: DU20916565 | I2: AR-NEUQUÉN | J2: TECPETROL S.A. | K2: Mamani Carlos Walter | L2: FPF-FN0940 | N2: Lusso Mauricio Ricardo | O2: =VLOOKUP(L2,CECOs!A:B,2,0) -> Sueldos TECPE | P2: =VLOOKUP(B:B,CECOs!G:I,3,FALSE) -> #N/A | Q2: =IF(_xlfn.XLOOKUP(L2,CECOs!A:A,CECOs!C:C,"")="",K2,_xlfn.XLOOKUP(L2,CECOs!A:A,CECOs!C:C,"")) -> Mamani Carlos Walter | R2: EFIS | S2: NQN | T2: 1005464 | U2: O&M Services | V2: WC | AB2: Headcount | AD2: SI
A3: 46266 | B3: 3417016 | C3: O&M Services Sr. Manager | D3: EFIS | E3: EFIS | G3: =Table1[[#This Row],[DESCRIPCION_POSICION]] -> O&M Services Sr. Manager | H3: DU29109359 | I3: AR-NEUQUÉN | J3: TECPETROL S.A. | K3: Lusso Mauricio Ricardo | L3: FPF-FN0940 | N3: Fabro Facundo | O3: =VLOOKUP(L3,CECOs!A:B,2,0) -> Sueldos TECPE | P3: =VLOOKUP(B:B,CECOs!G:I,3,FALSE) -> #N/A | Q3: =IF(_xlfn.XLOOKUP(L3,CECOs!A:A,CECOs!C:C,"")="",K3,_xlfn.XLOOKUP(L3,CECOs!A:A,CECOs!C:C,"")) -> Lusso Mauricio Ricardo | R3: EFIS | S3: NQN | U3: O&M Services | V3: WC | AB3: Headcount | AD3: SI
A4: 46266 | B4: 3197992 | C4: Maintenance Services Manager | D4: EFIS | E4: EFIS | G4: =Table1[[#This Row],[DESCRIPCION_POSICION]] -> Maintenance Services Manager | H4: DU28636995 | I4: AR-NEUQUÉN | J4: TECPETROL S.A. | K4: Fabro Facundo | L4: FPF-FN0940 | N4: Batallan Pablo Alejandro | O4: =VLOOKUP(L4,CECOs!A:B,2,0) -> Sueldos TECPE | P4: =VLOOKUP(B:B,CECOs!G:I,3,FALSE) -> #N/A | Q4: =IF(_xlfn.XLOOKUP(L4,CECOs!A:A,CECOs!C:C,"")="",K4,_xlfn.XLOOKUP(L4,CECOs!A:A,CECOs!C:C,"")) -> Fabro Facundo | R4: EFIS | S4: NQN | T4: 1016733 | U4: O&M Services | V4: WC | AB4: Headcount | AD4: SI
A5: 46266 | B5: 3294913 | C5: Operations Services Manager | D5: EFIS | E5: EFIS | G5: =Table1[[#This Row],[DESCRIPCION_POSICION]] -> Operations Services Manager | H5: DU33774464 | I5: AR-NEUQUÉN | J5: TECPETROL S.A. | K5: Fabro Facundo | L5: FPF-FN0940 | N5: Beloqui Leandro | O5: =VLOOKUP(L5,CECOs!A:B,2,0) -> Sueldos TECPE | P5: =VLOOKUP(B:B,CECOs!G:I,3,FALSE) -> #N/A | Q5: =IF(_xlfn.XLOOKUP(L5,CECOs!A:A,CECOs!C:C,"")="",K5,_xlfn.XLOOKUP(L5,CECOs!A:A,CECOs!C:C,"")) -> Fabro Facundo | R5: EFIS | S5: NQN | T5: 1016735 | U5: O&M Services | V5: WC | AB5: Headcount | AD5: SI
A6: 46266 | B6: 3364085 | C6: O&M Optimization Process Analyst | D6: EFIS | E6: EFIS | G6: =Table1[[#This Row],[DESCRIPCION_POSICION]] -> O&M Optimization Process Analyst | H6: DU40927304 | I6: AR-NEUQUÉN | J6: TECPETROL S.A. | K6: Lusso Mauricio Ricardo | L6: FPF-FN0940 | N6: Gili Arianna | O6: =VLOOKUP(L6,CECOs!A:B,2,0) -> Sueldos TECPE | P6: =VLOOKUP(B:B,CECOs!G:I,3,FALSE) -> #N/A | Q6: =IF(_xlfn.XLOOKUP(L6,CECOs!A:A,CECOs!C:C,"")="",K6,_xlfn.XLOOKUP(L6,CECOs!A:A,CECOs!C:C,"")) -> Lusso Mauricio Ricardo | R6: EFIS | S6: NQN | T6: 1016737 | U6: O&M Services | V6: WC | AB6: Headcount | AD6: SI
A7: 46266 | B7: 3392801 | C7: Maintenance Services Coordinator | D7: EFIS | E7: EFIS | G7: =Table1[[#This Row],[DESCRIPCION_POSICION]] -> Maintenance Services Coordinator | H7: DU28063207 | I7: AR-NEUQUÉN | J7: Energy Field Services | K7: Batallan Pablo Alejandro | L7: EFR-FN0920 | N7: Huarte Esteban | O7: =VLOOKUP(L7,CECOs!A:B,2,0) -> Facilitadores FP | P7: =VLOOKUP(B:B,CECOs!G:I,3,FALSE) -> FacilitadordeServicios | Q7: =IF(_xlfn.XLOOKUP(L7,CECOs!A:A,CECOs!C:C,"")="",K7,_xlfn.XLOOKUP(L7,CECOs!A:A,CECOs!C:C,"")) -> Batallan Pablo Alejandro | R7: EFIS | S7: NQN | T7: 1016733 | U7: O&M Services | V7: WC | AB7: Headcount | AD7: SI
A8: 46266 | B8: 3392802 | C8: Operations Services Coordinator | D8: EFIS | E8: EFIS | G8: =Table1[[#This Row],[DESCRIPCION_POSICION]] -> Operations Services Coordinator | H8: DU32090502 | I8: AR-NEUQUÉN | J8: Energy Field Services | K8: Batallan Pablo Alejandro | L8: EFR-FN0920 | N8: Cordova Daniela Emiliana | O8: =VLOOKUP(L8,CECOs!A:B,2,0) -> Facilitadores FP | P8: =VLOOKUP(B:B,CECOs!G:I,3,FALSE) -> FacilitadordeServicios | Q8: =IF(_xlfn.XLOOKUP(L8,CECOs!A:A,CECOs!C:C,"")="",K8,_xlfn.XLOOKUP(L8,CECOs!A:A,CECOs!C:C,"")) -> Batallan Pablo Alejandro | R8: EFIS | S8: NQN | T8: 1016733 | U8: O&M Services | V8: WC | AB8: Headcount | AD8: SI
A9: 46266 | B9: 3392803 | C9: Maintenance Services Coordinator | D9: EFIS | E9: EFIS | G9: =Table1[[#This Row],[DESCRIPCION_POSICION]] -> Maintenance Services Coordinator | H9: DU34666188 | I9: AR-NEUQUÉN | J9: Energy Field Services | K9: Batallan Pablo Alejandro | L9: EFR-FN0920 | N9: Altamiranda Leandro Damian | O9: =VLOOKUP(L9,CECOs!A:B,2,0) -> Facilitadores FP | P9: =VLOOKUP(B:B,CECOs!G:I,3,FALSE) -> FacilitadordeServicios | Q9: =IF(_xlfn.XLOOKUP(L9,CECOs!A:A,CECOs!C:C,"")="",K9,_xlfn.XLOOKUP(L9,CECOs!A:A,CECOs!C:C,"")) -> Batallan Pablo Alejandro | R9: EFIS | S9: NQN | T9: 1016733 | U9: O&M Services | V9: WC | AB9: Headcount | AD9: SI
A10: 46266 | B10: 3392804 | C10: Production Services Coordinator | D10: EFIS | E10: EFIS | G10: =Table1[[#This Row],[DESCRIPCION_POSICION]] -> Production Services Coordinator | H10: DU24131475 | I10: AR-NEUQUÉN | J10: Energy Field Services | K10: Lopez Rodrigo Gaston | L10: EFR-FN2007 | N10: Macias Ceferino Oscar | O10: =VLOOKUP(L10,CECOs!A:B,2,0) -> Supervisores Well Services | P10: =VLOOKUP(B:B,CECOs!G:I,3,FALSE) -> FacilitadordeServicios | Q10: =IF(_xlfn.XLOOKUP(L10,CECOs!A:A,CECOs!C:C,"")="",K10,_xlfn.XLOOKUP(L10,CECOs!A:A,CECOs!C:C,"")) -> Lopez Rodrigo Gaston | R10: EFIS | S10: NQN | T10: 1016735 | U10: O&M Services | V10: WC | AB10: Headcount | AD10: SI
A11: 46266 | B11: 3392805 | C11: Plants Services Coordinator | D11: EFIS | E11: EFIS | G11: =Table1[[#This Row],[DESCRIPCION_POSICION]] -> Plants Services Coordinator | H11: DU32195174 | I11: AR-NEUQUÉN | J11: Energy Field Services | K11: Lopez Rodrigo Gaston | L11: EFR-FN0900 | N11: Bechara Lucas Antonio | O11: =VLOOKUP(L11,CECOs!A:B,2,0) -> Facilitadores CONV | P11: =VLOOKUP(B:B,CECOs!G:I,3,FALSE) -> FacilitadordeServicios | Q11: =IF(_xlfn.XLOOKUP(L11,CECOs!A:A,CECOs!C:C,"")="",K11,_xlfn.XLOOKUP(L11,CECOs!A:A,CECOs!C:C,"")) -> Lopez Rodrigo Gaston | R11: EFIS | S11: NQN | T11: 1016735 | U11: O&M Services | V11: WC | AB11: Headcount | AD11: SI
A12: 46266 | B12: 3392806 | C12: Operations Services Coordinator | D12: EFIS | E12: EFIS | G12: =Table1[[#This Row],[DESCRIPCION_POSICION]] -> Operations Services Coordinator | H12: DU30191811 | I12: AR-NEUQUÉN | J12: Energy Field Services | K12: Lopez Rodrigo Gaston | L12: EFR-FN0920 | N12: Casal Gustavo Daniel | O12: =VLOOKUP(L12,CECOs!A:B,2,0) -> Facilitadores FP | P12: =VLOOKUP(B:B,CECOs!G:I,3,FALSE) -> FacilitadordeServicios | Q12: =IF(_xlfn.XLOOKUP(L12,CECOs!A:A,CECOs!C:C,"")="",K12,_xlfn.XLOOKUP(L12,CECOs!A:A,CECOs!C:C,"")) -> Lopez Rodrigo Gaston | R12: EFIS | S12: NQN | T12: 1016735 | U12: O&M Services | V12: WC | AB12: Headcount | AD12: SI
A13: 46266 | B13: 3392808 | C13: Technical Training Specialist | D13: EFIS | E13: EFIS | G13: =Table1[[#This Row],[DESCRIPCION_POSICION]] -> Technical Training Specialist | H13: DU36800803 | I13: AR-NEUQUÉN | J13: Energy Field Services | K13: Lopez Rodrigo Gaston | L13: EFR-FN0920 | N13: Poblete Matias Ezequiel | O13: =VLOOKUP(L13,CECOs!A:B,2,0) -> Facilitadores FP | P13: =VLOOKUP(B:B,CECOs!G:I,3,FALSE) -> FacilitadordeServicios | Q13: =IF(_xlfn.XLOOKUP(L13,CECOs!A:A,CECOs!C:C,"")="",K13,_xlfn.XLOOKUP(L13,CECOs!A:A,CECOs!C:C,"")) -> Lopez Rodrigo Gaston | R13: EFIS | S13: NQN | T13: 1016735 | U13: O&M Services | V13: WC | AB13: Headcount | AD13: SI
A14: 46266 | B14: 3406970 | C14: Oficial Especializado de Oficios | D14: EFIS | E14: EFIS | G14: =Table1[[#This Row],[DESCRIPCION_POSICION]] -> Oficial Especializado de Oficios | H14: DU47368614 | I14: AR-NEUQUÉN | J14: Energy Field Services | K14: Cordova Daniela Emiliana | L14: EFF-FP0921 | N14: Gonzalez Mendez Simon | O14: =VLOOKUP(L14,CECOs!A:B,2,0) -> Mtto Mecánico FP | P14: =VLOOKUP(B:B,CECOs!G:I,3,FALSE) -> Relevomantenimiento | Q14: =IF(_xlfn.XLOOKUP(L14,CECOs!A:A,CECOs!C:C,"")="",K14,_xlfn.XLOOKUP(L14,CECOs!A:A,CECOs!C:C,"")) -> CORDOVA, DANIELA / ALTAMIRANDA, LEANDRO | R14: EFIS | S14: NQN | U14: Maintenance | V14: BC | AB14: Headcount | AD14: SI
A15: 46266 | B15: 3414076 | C15: Maintenance Supervisor | D15: EFIS | E15: EFIS | G15: =Table1[[#This Row],[DESCRIPCION_POSICION]] -> Maintenance Supervisor | H15: DU40778151 | I15: AR-NEUQUÉN | J15: Energy Field Services | K15: Segura Alejandro | L15: EFF-FN1000 | N15: Gazzola Ezequiel | O15: =VLOOKUP(L15,CECOs!A:B,2,0) -> PJ TLM | P15: =VLOOKUP(B:B,CECOs!G:I,3,FALSE) -> Supervisoroperativo/Producción | Q15: =IF(_xlfn.XLOOKUP(L15,CECOs!A:A,CECOs!C:C,"")="",K15,_xlfn.XLOOKUP(L15,CECOs!A:A,CECOs!C:C,"")) -> Segura Alejandro | R15: EFIS | S15: NQN | U15: Maintenance | V15: WC | AB15: Headcount | AD15: SI
A16: 46266 | B16: 3392809 | C16: O&M Planning Analyst | D16: EFIS | E16: EFIS | G16: =Table1[[#This Row],[DESCRIPCION_POSICION]] -> O&M Planning Analyst | H16: DU41254675 | I16: AR-NEUQUÉN | J16: TECPETROL S.A. | K16: Gili Arianna | L16: FPF-FN0940 | N16: Baza Coseani Luisina | O16: =VLOOKUP(L16,CECOs!A:B,2,0) -> Sueldos TECPE | P16: =VLOOKUP(B:B,CECOs!G:I,3,FALSE) -> #N/A | Q16: =IF(_xlfn.XLOOKUP(L16,CECOs!A:A,CECOs!C:C,"")="",K16,_xlfn.XLOOKUP(L16,CECOs!A:A,CECOs!C:C,"")) -> Gili Arianna | R16: EFIS | S16: NQN | T16: 1016737 | U16: O&M Services | V16: WC | AB16: Headcount | AD16: SI
A17: 46266 | B17: 33928091 | C17: O&M Planning trainee | D17: EFIS | E17: EFIS | H17: DU46293912 | I17: AR-NEUQUÉN | J17: TECPETROL S.A. | K17: Gili Arianna | L17: FPF-FN0940 | N17: Vidic Alenka | O17: =VLOOKUP(L17,CECOs!A:B,2,0) -> Sueldos TECPE | P17: =VLOOKUP(B:B,CECOs!G:I,3,FALSE) -> #N/A | Q17: =IF(_xlfn.XLOOKUP(L17,CECOs!A:A,CECOs!C:C,"")="",K17,_xlfn.XLOOKUP(L17,CECOs!A:A,CECOs!C:C,"")) -> Gili Arianna | R17: EFIS | S17: NQN | U17: O&M Services | V17: WC
A18: 46266 | B18: 3392810 | C18: Accounts Payable Analyst | D18: EFIS | E18: EFIS | G18: =Table1[[#This Row],[DESCRIPCION_POSICION]] -> Accounts Payable Analyst | H18: DU43137970 | I18: AR-NEUQUÉN | J18: TECPETROL S.A. | K18: Romano Mariano Bruno | L18: FPF-FN0940 | N18: Sandalich Victoria | O18: =VLOOKUP(L18,CECOs!A:B,2,0) -> Sueldos TECPE | P18: =VLOOKUP(B:B,CECOs!G:I,3,FALSE) -> #N/A | Q18: =IF(_xlfn.XLOOKUP(L18,CECOs!A:A,CECOs!C:C,"")="",K18,_xlfn.XLOOKUP(L18,CECOs!A:A,CECOs!C:C,"")) -> Romano Mariano Bruno | R18: EFIS | S18: NQN | T18: 1000268 | U18: Adm. & Finance Neuquén | V18: WC | AB18: Headcount | AD18: SI
A19: 46266 | B19: 3392811 | C19: HRBP Analyst | D19: EFIS | E19: EFIS | G19: =Table1[[#This Row],[DESCRIPCION_POSICION]] -> HRBP Analyst | H19: DU39076574 | I19: AR-NEUQUÉN | J19: Energy Field Services | K19: Corbalan Federico Martin | L19: EFR-FN0941 | N19: Barrera Anahi Malen | O19: =VLOOKUP(L19,CECOs!A:B,2,0) -> Indirectos PRR | P19: =VLOOKUP(B:B,CECOs!G:I,3,FALSE) -> Personalnooperativo | Q19: =IF(_xlfn.XLOOKUP(L19,CECOs!A:A,CECOs!C:C,"")="",K19,_xlfn.XLOOKUP(L19,CECOs!A:A,CECOs!C:C,"")) -> Corbalan Federico Martin | R19: EFIS | S19: NQN | T19: 1005464 | U19: Human Resources | V19: WC | AB19: Headcount | AD19: SI
A20: 46266 | B20: 3392812 | C20: HRBP Sr. Analyst | D20: EFIS | E20: EFIS | G20: =Table1[[#This Row],[DESCRIPCION_POSICION]] -> HRBP Sr. Analyst | H20: DU36801186 | I20: AR-NEUQUÉN | J20: Energy Field Services | K20: Corbalan Federico Martin | L20: EFR-FN0941 | N20: Tarifeño Ernesto Eduardo | O20: =VLOOKUP(L20,CECOs!A:B,2,0) -> Indirectos PRR | P20: =VLOOKUP(B:B,CECOs!G:I,3,FALSE) -> Personalnooperativo | Q20: =IF(_xlfn.XLOOKUP(L20,CECOs!A:A,CECOs!C:C,"")="",K20,_xlfn.XLOOKUP(L20,CECOs!A:A,CECOs!C:C,"")) -> Corbalan Federico Martin | R20: EFIS | S20: NQN | T20: 1005464 | U20: Human Resources | V20: WC | AB20: Headcount | AD20: SI
A21: 46266 | B21: 3423705 | C21: HRBP Sr. Analyst | D21: EFIS | E21: EFIS | G21: =Table1[[#This Row],[DESCRIPCION_POSICION]] -> HRBP Sr. Analyst | H21: DU36257444 | I21: AR-NEUQUÉN | J21: Energy Field Services | K21: Corbalan Federico Martin | L21: EFR-FN0941 | N21: Soria Agustin Gabriel | O21: =VLOOKUP(L21,CECOs!A:B,2,0) -> Indirectos PRR | P21: =VLOOKUP(B:B,CECOs!G:I,3,FALSE) -> Personalnooperativo | Q21: =IF(_xlfn.XLOOKUP(L21,CECOs!A:A,CECOs!C:C,"")="",K21,_xlfn.XLOOKUP(L21,CECOs!A:A,CECOs!C:C,"")) -> Corbalan Federico Martin | R21: EFIS | S21: NQN | T21: 1005464 | U21: Human Resources | V21: WC | AB21: Headcount | AD21: SI
A22: 46266 | B22: 3437875 | C22: HRBP Analyst | D22: EFIS | E22: EFIS | G22: =Table1[[#This Row],[DESCRIPCION_POSICION]] -> HRBP Analyst | H22: DU43084808 | I22: AR-NEUQUÉN | J22: Energy Field Services | K22: Corbalan Federico Martin | L22: EFR-FN0941 | N22: Ulla Milagros | O22: =VLOOKUP(L22,CECOs!A:B,2,0) -> Indirectos PRR | P22: =VLOOKUP(B:B,CECOs!G:I,3,FALSE) -> Personalnooperativo | Q22: =IF(_xlfn.XLOOKUP(L22,CECOs!A:A,CECOs!C:C,"")="",K22,_xlfn.XLOOKUP(L22,CECOs!A:A,CECOs!C:C,"")) -> Corbalan Federico Martin | R22: EFIS | S22: NQN | U22: Human Resources | V22: WC | AB22: Headcount | AD22: SI
A23: 46266 | B23: 3437846 | C23: Labor Relations Expert | D23: EFIS | E23: EFIS | G23: =Table1[[#This Row],[DESCRIPCION_POSICION]] -> Labor Relations Expert | I23: AR-NEUQUÉN | J23: Energy Field Services | K23: Gaisch Alejandro Hector | L23: EFR-FN0941 | N23: Vacante RL Sep/26 | O23: =VLOOKUP(L23,CECOs!A:B,2,0) -> Indirectos PRR | P23: =VLOOKUP(B:B,CECOs!G:I,3,FALSE) -> Personalnooperativo | Q23: =IF(_xlfn.XLOOKUP(L23,CECOs!A:A,CECOs!C:C,"")="",K23,_xlfn.XLOOKUP(L23,CECOs!A:A,CECOs!C:C,"")) -> Gaisch Alejandro Hector | R23: EFIS | S23: NQN | U23: Labor Relations & CORE | V23: WC | AB23: Headcount | AD23: SI
A24: 46266 | B24: 3392813 | C24: Labor Relations Expert | D24: EFIS | E24: EFIS | G24: =Table1[[#This Row],[DESCRIPCION_POSICION]] -> Labor Relations Expert | H24: DU30264777 | I24: AR-NEUQUÉN | J24: Energy Field Services | K24: Gaisch Alejandro Hector | L24: EFR-FN0941 | N24: Seguel Maria Fernanda | O24: =VLOOKUP(L24,CECOs!A:B,2,0) -> Indirectos PRR | P24: =VLOOKUP(B:B,CECOs!G:I,3,FALSE) -> Personalnooperativo | Q24: =IF(_xlfn.XLOOKUP(L24,CECOs!A:A,CECOs!C:C,"")="",K24,_xlfn.XLOOKUP(L24,CECOs!A:A,CECOs!C:C,"")) -> Gaisch Alejandro Hector | R24: EFIS | S24: NQN | T24: 1010254 | U24: Labor Relations & CORE | V24: WC | AB24: Headcount | AD24: SI
A25: 46266 | B25: 3392814 | C25: Quality Analyst | D25: EFIS | E25: EFIS | G25: =Table1[[#This Row],[DESCRIPCION_POSICION]] -> Quality Analyst | H25: DU36010010 | I25: AR-NEUQUÉN | J25: Energy Field Services | K25: Seri Walter Omar | L25: EFR-FN0941 | N25: Campora Camila María | O25: =VLOOKUP(L25,CECOs!A:B,2,0) -> Indirectos PRR | P25: =VLOOKUP(B:B,CECOs!G:I,3,FALSE) -> Personalnooperativo | Q25: =IF(_xlfn.XLOOKUP(L25,CECOs!A:A,CECOs!C:C,"")="",K25,_xlfn.XLOOKUP(L25,CECOs!A:A,CECOs!C:C,"")) -> Seri Walter Omar | R25: EFIS | S25: NQN | T25: 1013992 | U25: Quality | V25: WC | AB25: Headcount | AD25: SI
A26: 46266 | B26: 3392815 | C26: General Services Supervisor | D26: EFIS | E26: EFIS | G26: =Table1[[#This Row],[DESCRIPCION_POSICION]] -> General Services Supervisor | H26: DU33067280 | I26: AR-NEUQUÉN | J26: Energy Field Services | K26: Zuluaga Gabriel | L26: EFR-FN0941 | N26: Rizzo Sebastian | O26: =VLOOKUP(L26,CECOs!A:B,2,0) -> Indirectos PRR | P26: =VLOOKUP(B:B,CECOs!G:I,3,FALSE) -> Supervisoroperativo/Producción | Q26: =IF(_xlfn.XLOOKUP(L26,CECOs!A:A,CECOs!C:C,"")="",K26,_xlfn.XLOOKUP(L26,CECOs!A:A,CECOs!C:C,"")) -> Zuluaga Gabriel | R26: EFIS | S26: NQN | T26: 1005464 | U26: General Services | V26: WC | AB26: Headcount | AD26: SI
A27: 46266 | B27: 3392816 | C27: HSE Sr. Supervisor | D27: EFIS | E27: EFIS | G27: =Table1[[#This Row],[DESCRIPCION_POSICION]] -> HSE Sr. Supervisor | H27: DU36669185 | I27: AR-NEUQUÉN | J27: Energy Field Services | K27: Chazarreta Jose Antonio | L27: EFR-FN0945 | N27: Figueroa Franco Martin | O27: =VLOOKUP(L27,CECOs!A:B,2,0) -> SAS PRR | P27: =VLOOKUP(B:B,CECOs!G:I,3,FALSE) -> SupervisoresSAS/OT | Q27: =IF(_xlfn.XLOOKUP(L27,CECOs!A:A,CECOs!C:C,"")="",K27,_xlfn.XLOOKUP(L27,CECOs!A:A,CECOs!C:C,"")) -> Chazarreta Jose Antonio | R27: EFIS | S27: NQN | T27: 1005233 | U27: Health & Safety | V27: WC | AB27: Headcount | AD27: SI
A28: 46266 | B28: 3392817 | C28: HSE Sr. Supervisor | D28: EFIS | E28: EFIS | G28: =Table1[[#This Row],[DESCRIPCION_POSICION]] -> HSE Sr. Supervisor | H28: DU33926407 | I28: AR-NEUQUÉN | J28: Energy Field Services | K28: Chazarreta Jose Antonio | L28: EFR-FN0945 | N28: Mora Federico | O28: =VLOOKUP(L28,CECOs!A:B,2,0) -> SAS PRR | P28: =VLOOKUP(B:B,CECOs!G:I,3,FALSE) -> SupervisoresSAS/OT | Q28: =IF(_xlfn.XLOOKUP(L28,CECOs!A:A,CECOs!C:C,"")="",K28,_xlfn.XLOOKUP(L28,CECOs!A:A,CECOs!C:C,"")) -> Chazarreta Jose Antonio | R28: EFIS | S28: NQN | T28: 1005233 | U28: Health & Safety | V28: WC | AB28: Headcount | AD28: SI
A29: 46266 | B29: 3392818 | C29: HSE Sr. Supervisor | D29: EFIS | E29: EFIS | G29: =Table1[[#This Row],[DESCRIPCION_POSICION]] -> HSE Sr. Supervisor | H29: DU28387841 | I29: AR-NEUQUÉN | J29: Energy Field Services | K29: Chazarreta Jose Antonio | L29: EFR-FN0945 | N29: Sea Oscar Ariel | O29: =VLOOKUP(L29,CECOs!A:B,2,0) -> SAS PRR | P29: =VLOOKUP(B:B,CECOs!G:I,3,FALSE) -> SupervisoresSAS/OT | Q29: =IF(_xlfn.XLOOKUP(L29,CECOs!A:A,CECOs!C:C,"")="",K29,_xlfn.XLOOKUP(L29,CECOs!A:A,CECOs!C:C,"")) -> Chazarreta Jose Antonio | R29: EFIS | S29: NQN | T29: 1005233 | U29: Health & Safety | V29: WC | AB29: Headcount | AD29: SI
A30: 46266 | B30: 3392819 | C30: HSE Sr. Supervisor | D30: EFIS | E30: EFIS | G30: =Table1[[#This Row],[DESCRIPCION_POSICION]] -> HSE Sr. Supervisor | H30: DU33885206 | I30: AR-NEUQUÉN | J30: Energy Field Services | K30: Chazarreta Jose Antonio | L30: EFR-FN0945 | N30: Palma Belen del Milagro | O30: =VLOOKUP(L30,CECOs!A:B,2,0) -> SAS PRR | P30: =VLOOKUP(B:B,CECOs!G:I,3,FALSE) -> SupervisoresSAS/OT | Q30: =IF(_xlfn.XLOOKUP(L30,CECOs!A:A,CECOs!C:C,"")="",K30,_xlfn.XLOOKUP(L30,CECOs!A:A,CECOs!C:C,"")) -> Chazarreta Jose Antonio | R30: EFIS | S30: NQN | T30: 1005233 | U30: Health & Safety | V30: WC | AB30: Headcount | AD30: SI
A31: 46266 | B31: 3392820 | C31: HSE Sr. Supervisor | D31: EFIS | E31: EFIS | G31: =Table1[[#This Row],[DESCRIPCION_POSICION]] -> HSE Sr. Supervisor | H31: DU23918152 | I31: AR-NEUQUÉN | J31: Energy Field Services | K31: Lemes Mariana De Los Angeles | L31: EFR-FN0945 | N31: Huaiquiñir Juan Jose | O31: =VLOOKUP(L31,CECOs!A:B,2,0) -> SAS PRR | P31: =VLOOKUP(B:B,CECOs!G:I,3,FALSE) -> SupervisoresSAS/OT | Q31: =IF(_xlfn.XLOOKUP(L31,CECOs!A:A,CECOs!C:C,"")="",K31,_xlfn.XLOOKUP(L31,CECOs!A:A,CECOs!C:C,"")) -> Lemes Mariana De Los Angeles | R31: EFIS | S31: NQN | T31: 1005233 | U31: Health & Safety | V31: WC | AB31: Headcount | AD31: SI
A32: 46266 | B32: 3392821 | C32: HSE Sr. Supervisor | D32: EFIS | E32: EFIS | G32: =Table1[[#This Row],[DESCRIPCION_POSICION]] -> HSE Sr. Supervisor | H32: DU28254170 | I32: AR-NEUQUÉN | J32: Energy Field Services | K32: Lemes Mariana De Los Angeles | L32: EFR-FN0945 | N32: Galdame Carlos David | O32: =VLOOKUP(L32,CECOs!A:B,2,0) -> SAS PRR | P32: =VLOOKUP(B:B,CECOs!G:I,3,FALSE) -> SupervisoresSAS/OT | Q32: =IF(_xlfn.XLOOKUP(L32,CECOs!A:A,CECOs!C:C,"")="",K32,_xlfn.XLOOKUP(L32,CECOs!A:A,CECOs!C:C,"")) -> Lemes Mariana De Los Angeles | R32: EFIS | S32: NQN | T32: 1005233 | U32: Health & Safety | V32: WC | AB32: Headcount | AD32: SI
A33: 46266 | B33: 3424838 | C33: Operations Services Coordinator | D33: EFIS | E33: EFIS | G33: =Table1[[#This Row],[DESCRIPCION_POSICION]] -> Operations Services Coordinator | H33: DU24260286 | I33: AR-NEUQUÉN | J33: Energy Field Services | K33: Lopez Rodrigo Gaston | L33: EFR-2E0970 | N33: Mercado Mauricio Edgardo | O33: =VLOOKUP(L33,CECOs!A:B,2,0) -> Facilitadores LT2E | P33: =VLOOKUP(B:B,CECOs!G:I,3,FALSE) -> FacilitadordeServicios | Q33: =IF(_xlfn.XLOOKUP(L33,CECOs!A:A,CECOs!C:C,"")="",K33,_xlfn.XLOOKUP(L33,CECOs!A:A,CECOs!C:C,"")) -> Lopez Rodrigo Gaston | R33: EFIS | S33: NQN | U33: O&M Services | V33: WC | AB33: Headcount | AD33: SI
A34: 46266 | B34: 3424839 | C34: Operations Services Coordinator | D34: EFIS | E34: EFIS | G34: =Table1[[#This Row],[DESCRIPCION_POSICION]] -> Operations Services Coordinator | H34: DU27841592 | I34: AR-NEUQUÉN | J34: Energy Field Services | K34: Lopez Rodrigo Gaston | L34: EFR-2E0970 | N34: Fredes Ruben Oscar | O34: =VLOOKUP(L34,CECOs!A:B,2,0) -> Facilitadores LT2E | P34: =VLOOKUP(B:B,CECOs!G:I,3,FALSE) -> FacilitadordeServicios | Q34: =IF(_xlfn.XLOOKUP(L34,CECOs!A:A,CECOs!C:C,"")="",K34,_xlfn.XLOOKUP(L34,CECOs!A:A,CECOs!C:C,"")) -> Lopez Rodrigo Gaston | R34: EFIS | S34: NQN | U34: O&M Services | V34: WC | AB34: Headcount | AD34: SI
A35: 46266 | B35: 3395761 | C35: Medical Assistant | D35: EFIS | E35: EFIS | G35: =Table1[[#This Row],[DESCRIPCION_POSICION]] -> Medical Assistant | H35: DU33135662 | I35: AR-NEUQUÉN | J35: Energy Field Services | K35: Martel Maximiliano Jose Tomas | L35: EFR-FN0945 | N35: Feruglio Adrian Federico | O35: =VLOOKUP(L35,CECOs!A:B,2,0) -> SAS PRR | P35: =VLOOKUP(B:B,CECOs!G:I,3,FALSE) -> Personalnooperativo | Q35: =IF(_xlfn.XLOOKUP(L35,CECOs!A:A,CECOs!C:C,"")="",K35,_xlfn.XLOOKUP(L35,CECOs!A:A,CECOs!C:C,"")) -> Martel Maximiliano Jose Tomas | R35: EFIS | S35: NQN | T35: 1005233 | U35: Health & Safety | V35: WC | AB35: Headcount | AD35: SI
A36: 46266 | B36: 3395760 | C36: Medical Assistant | D36: EFIS | E36: EFIS | G36: =Table1[[#This Row],[DESCRIPCION_POSICION]] -> Medical Assistant | H36: DU26638146 | I36: AR-NEUQUÉN | J36: Energy Field Services | K36: Martel Maximiliano Jose Tomas | L36: EFR-FN0945 | N36: Schlosser Adolfo Julio | O36: =VLOOKUP(L36,CECOs!A:B,2,0) -> SAS PRR | P36: =VLOOKUP(B:B,CECOs!G:I,3,FALSE) -> Personalnooperativo | Q36: =IF(_xlfn.XLOOKUP(L36,CECOs!A:A,CECOs!C:C,"")="",K36,_xlfn.XLOOKUP(L36,CECOs!A:A,CECOs!C:C,"")) -> Martel Maximiliano Jose Tomas | R36: EFIS | S36: NQN | T36: 1005233 | U36: Health & Safety | V36: WC | AB36: Headcount | AD36: SI
A37: 46266 | B37: 3392823 | C37: Environmental Supervisor | D37: EFIS | E37: EFIS | G37: =Table1[[#This Row],[DESCRIPCION_POSICION]] -> Environmental Supervisor | H37: DU33316128 | I37: AR-NEUQUÉN | J37: Energy Field Services | K37: Carreño Venegas Cecilia | L37: EFR-FN0945 | N37: Leiva Ricardo Alejandro | O37: =VLOOKUP(L37,CECOs!A:B,2,0) -> SAS PRR | P37: =VLOOKUP(B:B,CECOs!G:I,3,FALSE) -> SupervisoresSAS/OT | Q37: =IF(_xlfn.XLOOKUP(L37,CECOs!A:A,CECOs!C:C,"")="",K37,_xlfn.XLOOKUP(L37,CECOs!A:A,CECOs!C:C,"")) -> Carreño Venegas Cecilia | R37: EFIS | S37: NQN | T37: 1010264 | U37: Environmental | V37: WC | AB37: Headcount | AD37: SI
A38: 46266 | B38: 3414072 | C38: Environmental Sr. Supervisor | D38: EFIS | E38: EFIS | G38: =Table1[[#This Row],[DESCRIPCION_POSICION]] -> Environmental Sr. Supervisor | H38: DU36344221 | I38: AR-NEUQUÉN | J38: Energy Field Services | K38: Carreño Venegas Cecilia | L38: EFR-FN0945 | N38: Acuña Fernanda Natali | O38: =VLOOKUP(L38,CECOs!A:B,2,0) -> SAS PRR | P38: =VLOOKUP(B:B,CECOs!G:I,3,FALSE) -> SupervisoresSAS/OT | Q38: =IF(_xlfn.XLOOKUP(L38,CECOs!A:A,CECOs!C:C,"")="",K38,_xlfn.XLOOKUP(L38,CECOs!A:A,CECOs!C:C,"")) -> Carreño Venegas Cecilia | R38: EFIS | S38: NQN | U38: Environmental | V38: WC | AB38: Headcount | AD38: SI
A39: 46266 | B39: 3392824 | C39: Health Auxiliar | D39: EFIS | E39: EFIS | G39: =Table1[[#This Row],[DESCRIPCION_POSICION]] -> Health Auxiliar | H39: DU29463906 | I39: AR-NEUQUÉN | J39: Energy Field Services | K39: Martel Maximiliano Jose Tomas | L39: EFR-FN0945 | N39: Prieto Beatriz Alejandra | O39: =VLOOKUP(L39,CECOs!A:B,2,0) -> SAS PRR | P39: =VLOOKUP(B:B,CECOs!G:I,3,FALSE) -> Personalnooperativo | Q39: =IF(_xlfn.XLOOKUP(L39,CECOs!A:A,CECOs!C:C,"")="",K39,_xlfn.XLOOKUP(L39,CECOs!A:A,CECOs!C:C,"")) -> Martel Maximiliano Jose Tomas | R39: EFIS | S39: NQN | T39: 1005233 | U39: Health & Safety | V39: WC | AB39: Headcount | AD39: SI
A40: 46266 | B40: 3392825 | C40: Operations Technology Maint. Engineer | D40: EFIS | E40: EFIS | G40: =Table1[[#This Row],[DESCRIPCION_POSICION]] -> Operations Technology Maint. Engineer | H40: DU33993061 | I40: AR-NEUQUÉN | J40: Energy Field Services | K40: Contreras Fernando Andres | L40: EFR-FN0930 | N40: Crespillo Faur Adrian Alejandro | O40: =VLOOKUP(L40,CECOs!A:B,2,0) -> OT PRR | P40: =VLOOKUP(B:B,CECOs!G:I,3,FALSE) -> SupervisoresSAS/OT | Q40: =IF(_xlfn.XLOOKUP(L40,CECOs!A:A,CECOs!C:C,"")="",K40,_xlfn.XLOOKUP(L40,CECOs!A:A,CECOs!C:C,"")) -> Contreras Fernando Andres | R40: EFIS | S40: NQN | T40: 1010274 | U40: Maintenance | V40: WC | AB40: Headcount | AD40: SI
A41: 46266 | B41: 3392826 | C41: Operations Technology Maint. Engineer | D41: EFIS | E41: EFIS | G41: =Table1[[#This Row],[DESCRIPCION_POSICION]] -> Operations Technology Maint. Engineer | H41: DU31806630 | I41: AR-NEUQUÉN | J41: Energy Field Services | K41: Contreras Fernando Andres | L41: EFR-FN0930 | N41: Gonzalez Rodrigo Jeremias | O41: =VLOOKUP(L41,CECOs!A:B,2,0) -> OT PRR | P41: =VLOOKUP(B:B,CECOs!G:I,3,FALSE) -> SupervisoresSAS/OT | Q41: =IF(_xlfn.XLOOKUP(L41,CECOs!A:A,CECOs!C:C,"")="",K41,_xlfn.XLOOKUP(L41,CECOs!A:A,CECOs!C:C,"")) -> Contreras Fernando Andres | R41: EFIS | S41: NQN | T41: 1010274 | U41: Maintenance | V41: WC | AB41: Headcount | AD41: SI
A42: 46266 | B42: 3392827 | C42: Operations Technology Maint. Engineer | D42: EFIS | E42: EFIS | G42: =Table1[[#This Row],[DESCRIPCION_POSICION]] -> Operations Technology Maint. Engineer | H42: DU37518969 | I42: AR-NEUQUÉN | J42: Energy Field Services | K42: Contreras Fernando Andres | L42: EFR-FN0930 | N42: Forconi Enzo Ramiro | O42: =VLOOKUP(L42,CECOs!A:B,2,0) -> OT PRR | P42: =VLOOKUP(B:B,CECOs!G:I,3,FALSE) -> SupervisoresSAS/OT | Q42: =IF(_xlfn.XLOOKUP(L42,CECOs!A:A,CECOs!C:C,"")="",K42,_xlfn.XLOOKUP(L42,CECOs!A:A,CECOs!C:C,"")) -> Contreras Fernando Andres | R42: EFIS | S42: NQN | T42: 1010274 | U42: Maintenance | V42: WC | AB42: Headcount | AD42: SI
A43: 46266 | B43: 3392828 | C43: Operations Technology Maint. Engineer | D43: EFIS | E43: EFIS | G43: =Table1[[#This Row],[DESCRIPCION_POSICION]] -> Operations Technology Maint. Engineer | H43: DU95871315 | I43: AR-NEUQUÉN | J43: Energy Field Services | K43: Contreras Fernando Andres | L43: EFR-FN0930 | N43: Rodriguez Bordones Marcel Josue | O43: =VLOOKUP(L43,CECOs!A:B,2,0) -> OT PRR | P43: =VLOOKUP(B:B,CECOs!G:I,3,FALSE) -> SupervisoresSAS/OT | Q43: =IF(_xlfn.XLOOKUP(L43,CECOs!A:A,CECOs!C:C,"")="",K43,_xlfn.XLOOKUP(L43,CECOs!A:A,CECOs!C:C,"")) -> Contreras Fernando Andres | R43: EFIS | S43: NQN | T43: 1010274 | U43: Maintenance | V43: WC | AB43: Headcount | AD43: SI
A44: 46266 | B44: 3392829 | C44: Operations Technology Maint. Engineer | D44: EFIS | E44: EFIS | G44: =Table1[[#This Row],[DESCRIPCION_POSICION]] -> Operations Technology Maint. Engineer | H44: DU37943788 | I44: AR-NEUQUÉN | J44: Energy Field Services | K44: Contreras Fernando Andres | L44: EFR-FN0930 | N44: Lillo Mauricio | O44: =VLOOKUP(L44,CECOs!A:B,2,0) -> OT PRR | P44: =VLOOKUP(B:B,CECOs!G:I,3,FALSE) -> SupervisoresSAS/OT | Q44: =IF(_xlfn.XLOOKUP(L44,CECOs!A:A,CECOs!C:C,"")="",K44,_xlfn.XLOOKUP(L44,CECOs!A:A,CECOs!C:C,"")) -> Contreras Fernando Andres | R44: EFIS | S44: NQN | T44: 1010274 | U44: Maintenance | V44: WC | AB44: Headcount | AD44: SI
A45: 46266 | B45: 3392830 | C45: Operations Technology Maint. Engineer | D45: EFIS | E45: EFIS | G45: =Table1[[#This Row],[DESCRIPCION_POSICION]] -> Operations Technology Maint. Engineer | H45: DU34127114 | I45: AR-NEUQUÉN | J45: Energy Field Services | K45: Contreras Fernando Andres | L45: EFR-FN0930 | N45: Saenz Emiliano Jesus | O45: =VLOOKUP(L45,CECOs!A:B,2,0) -> OT PRR | P45: =VLOOKUP(B:B,CECOs!G:I,3,FALSE) -> SupervisoresSAS/OT | Q45: =IF(_xlfn.XLOOKUP(L45,CECOs!A:A,CECOs!C:C,"")="",K45,_xlfn.XLOOKUP(L45,CECOs!A:A,CECOs!C:C,"")) -> Contreras Fernando Andres | R45: EFIS | S45: NQN | T45: 1010274 | U45: Maintenance | V45: WC | AB45: Headcount | AD45: SI
A46: 46266 | B46: 3392831 | C46: Operations Technology Maint. Engineer | D46: EFIS | E46: EFIS | G46: =Table1[[#This Row],[DESCRIPCION_POSICION]] -> Operations Technology Maint. Engineer | H46: DU96032842 | I46: AR-NEUQUÉN | J46: Energy Field Services | K46: Contreras Fernando Andres | L46: EFR-FN0930 | N46: Suarez Jhoana Mariela | O46: =VLOOKUP(L46,CECOs!A:B,2,0) -> OT PRR | P46: =VLOOKUP(B:B,CECOs!G:I,3,FALSE) -> SupervisoresSAS/OT | Q46: =IF(_xlfn.XLOOKUP(L46,CECOs!A:A,CECOs!C:C,"")="",K46,_xlfn.XLOOKUP(L46,CECOs!A:A,CECOs!C:C,"")) -> Contreras Fernando Andres | R46: EFIS | S46: NQN | T46: 1010274 | U46: Maintenance | V46: WC | AB46: Headcount | AD46: SI
A47: 46266 | B47: 3418339 | C47: Operations Technology Eng. Engineer | D47: EFIS | E47: EFIS | G47: =Table1[[#This Row],[DESCRIPCION_POSICION]] -> Operations Technology Eng. Engineer | H47: DU31316545 | I47: AR-NEUQUÉN | J47: Energy Field Services | K47: Schmidt Brian Eric | L47: EFR-FN0930 | N47: Marasco Nestor Damian | O47: =VLOOKUP(L47,CECOs!A:B,2,0) -> OT PRR | P47: =VLOOKUP(B:B,CECOs!G:I,3,FALSE) -> SupervisoresSAS/OT | Q47: =IF(_xlfn.XLOOKUP(L47,CECOs!A:A,CECOs!C:C,"")="",K47,_xlfn.XLOOKUP(L47,CECOs!A:A,CECOs!C:C,"")) -> Schmidt Brian Eric | R47: EFIS | S47: NQN | T47: 1010274 | U47: Maintenance | V47: WC | AB47: Headcount | AD47: SI
A48: 46266 | B48: 3418340 | C48: Operations Technology Eng. Engineer | D48: EFIS | E48: EFIS | G48: =Table1[[#This Row],[DESCRIPCION_POSICION]] -> Operations Technology Eng. Engineer | H48: DU39881413 | I48: AR-NEUQUÉN | J48: Energy Field Services | K48: Schmidt Brian Eric | L48: EFR-FN0930 | N48: Viluron Santiago Ezequiel | O48: =VLOOKUP(L48,CECOs!A:B,2,0) -> OT PRR | P48: =VLOOKUP(B:B,CECOs!G:I,3,FALSE) -> SupervisoresSAS/OT | Q48: =IF(_xlfn.XLOOKUP(L48,CECOs!A:A,CECOs!C:C,"")="",K48,_xlfn.XLOOKUP(L48,CECOs!A:A,CECOs!C:C,"")) -> Schmidt Brian Eric | R48: EFIS | S48: NQN | T48: 1010274 | U48: Maintenance | V48: WC | AB48: Headcount | AD48: SI
A49: 46266 | B49: 3392846 | C49: Integrity Supervisor | D49: EFIS | E49: EFIS | G49: =Table1[[#This Row],[DESCRIPCION_POSICION]] -> Integrity Supervisor | I49: AR-NEUQUÉN | J49: Energy Field Services | K49: Diaz Luis Alberto | L49: EFR-FN0931 | N49: Vacante Sup. Integridad | O49: =VLOOKUP(L49,CECOs!A:B,2,0) -> Integridad PRR | P49: =VLOOKUP(B:B,CECOs!G:I,3,FALSE) -> Supervisoroperativo/Producción | Q49: =IF(_xlfn.XLOOKUP(L49,CECOs!A:A,CECOs!C:C,"")="",K49,_xlfn.XLOOKUP(L49,CECOs!A:A,CECOs!C:C,"")) -> Diaz Luis Alberto | R49: EFIS | S49: NQN | T49: 1010274 | U49: Maintenance | V49: WC | AB49: Headcount | AD49: SI
A50: 46266 | B50: 3392868 | C50: Recorredor Especializado | D50: EFIS | E50: EFIS | G50: =Table1[[#This Row],[DESCRIPCION_POSICION]] -> Recorredor Especializado | H50: DU44103409 | I50: AR-NEUQUÉN | J50: Energy Field Services | K50: Bechara Lucas Antonio | L50: EFF-LB0901 | N50: Cheuquel Agustin Gabriel | O50: =VLOOKUP(L50,CECOs!A:B,2,0) -> Oper campo LBAS | P50: =VLOOKUP(B:B,CECOs!G:I,3,FALSE) -> OperadordeCampo | Q50: =IF(_xlfn.XLOOKUP(L50,CECOs!A:A,CECOs!C:C,"")="",K50,_xlfn.XLOOKUP(L50,CECOs!A:A,CECOs!C:C,"")) -> BECHARA, LUCAS ANTONIO | R50: EFIS | S50: NQN | T50: 1016735 | U50: Operations | V50: BC | AB50: Headcount | AD50: SI
A51: 46266 | B51: 3392834 | C51: Maintenance Sr. Supervisor | D51: EFIS | E51: EFIS | G51: =Table1[[#This Row],[DESCRIPCION_POSICION]] -> Maintenance Sr. Supervisor | H51: DU21381134 | I51: AR-NEUQUÉN | J51: Energy Field Services | K51: Sheffield Naiara Eileen | L51: EFR-FN0910 | N51: Olave Omar Luis | O51: =VLOOKUP(L51,CECOs!A:B,2,0) -> Supervisores Mtto | P51: =VLOOKUP(B:B,CECOs!G:I,3,FALSE) -> Supervisoroperativo/Producción | Q51: =IF(_xlfn.XLOOKUP(L51,CECOs!A:A,CECOs!C:C,"")="",K51,_xlfn.XLOOKUP(L51,CECOs!A:A,CECOs!C:C,"")) -> Sheffield Naiara Eileen | R51: EFIS | S51: NQN | T51: 1010274 | U51: Maintenance | V51: WC | AB51: Headcount | AD51: SI
A52: 46266 | B52: 3392835 | C52: Maintenance Sr. Supervisor | D52: EFIS | E52: EFIS | G52: =Table1[[#This Row],[DESCRIPCION_POSICION]] -> Maintenance Sr. Supervisor | H52: DU31950417 | I52: AR-NEUQUÉN | J52: Energy Field Services | K52: Sheffield Naiara Eileen | L52: EFR-FN0910 | N52: Martinez Marcos | O52: =VLOOKUP(L52,CECOs!A:B,2,0) -> Supervisores Mtto | P52: =VLOOKUP(B:B,CECOs!G:I,3,FALSE) -> Supervisoroperativo/Producción | Q52: =IF(_xlfn.XLOOKUP(L52,CECOs!A:A,CECOs!C:C,"")="",K52,_xlfn.XLOOKUP(L52,CECOs!A:A,CECOs!C:C,"")) -> Sheffield Naiara Eileen | R52: EFIS | S52: NQN | T52: 1010274 | U52: Maintenance | V52: WC | AB52: Headcount | AD52: SI
A53: 46266 | B53: 3401242 | C53: Maintenance Sr. Supervisor | D53: EFIS | E53: EFIS | G53: =Table1[[#This Row],[DESCRIPCION_POSICION]] -> Maintenance Sr. Supervisor | H53: DU33476887 | I53: AR-NEUQUÉN | J53: Energy Field Services | K53: Mazoue Juan Manuel | L53: EFR-FN0910 | N53: Bohl Damian Alfredo | O53: =VLOOKUP(L53,CECOs!A:B,2,0) -> Supervisores Mtto | P53: =VLOOKUP(B:B,CECOs!G:I,3,FALSE) -> Supervisoroperativo/Producción | Q53: =IF(_xlfn.XLOOKUP(L53,CECOs!A:A,CECOs!C:C,"")="",K53,_xlfn.XLOOKUP(L53,CECOs!A:A,CECOs!C:C,"")) -> Mazoue Juan Manuel | R53: EFIS | S53: NQN | T53: 1010274 | U53: Maintenance | V53: WC | AB53: Headcount | AD53: APROBADA
A54: 46266 | B54: 3437843 | C54: Operations Technology Eng. Engineer | D54: EFIS | E54: EFIS | G54: =Table1[[#This Row],[DESCRIPCION_POSICION]] -> Operations Technology Eng. Engineer | I54: AR-NEUQUÉN | J54: Energy Field Services | K54: Forte Federico | L54: EFR-FN0930 | N54: Vacante OT LT2E | O54: =VLOOKUP(L54,CECOs!A:B,2,0) -> OT PRR | P54: =VLOOKUP(B:B,CECOs!G:I,3,FALSE) -> #N/A | Q54: =IF(_xlfn.XLOOKUP(L54,CECOs!A:A,CECOs!C:C,"")="",K54,_xlfn.XLOOKUP(L54,CECOs!A:A,CECOs!C:C,"")) -> Forte Federico | R54: EFIS | S54: NQN | U54: Maintenance | V54: WC | AB54: Headcount | AD54: SI
A55: 46266 | B55: 3392836 | C55: Plant Lead Supervisor | D55: EFIS | E55: EFIS | G55: =Table1[[#This Row],[DESCRIPCION_POSICION]] -> Plant Lead Supervisor | H55: DU25173304 | I55: AR-NEUQUÉN | J55: Energy Field Services | K55: Doria Pablo Cesar | L55: EFF-FP0911 | N55: Inostroza Juan Marcelo | O55: =VLOOKUP(L55,CECOs!A:B,2,0) -> Operadores SALA EPF | P55: =VLOOKUP(B:B,CECOs!G:I,3,FALSE) -> #N/A | Q55: =IF(_xlfn.XLOOKUP(L55,CECOs!A:A,CECOs!C:C,"")="",K55,_xlfn.XLOOKUP(L55,CECOs!A:A,CECOs!C:C,"")) -> Doria Pablo Cesar | R55: EFIS | S55: NQN | T55: 1012899 | U55: Operations | V55: WC | AB55: Headcount | AD55: SI
A56: 46266 | B56: 3392837 | C56: Plant Lead Supervisor | D56: EFIS | E56: EFIS | G56: =Table1[[#This Row],[DESCRIPCION_POSICION]] -> Plant Lead Supervisor | H56: DU24825640 | I56: AR-NEUQUÉN | J56: Energy Field Services | K56: Doria Pablo Cesar | L56: EFF-FP0911 | N56: Pedrero Jorge Esteban | O56: =VLOOKUP(L56,CECOs!A:B,2,0) -> Operadores SALA EPF | P56: =VLOOKUP(B:B,CECOs!G:I,3,FALSE) -> #N/A | Q56: =IF(_xlfn.XLOOKUP(L56,CECOs!A:A,CECOs!C:C,"")="",K56,_xlfn.XLOOKUP(L56,CECOs!A:A,CECOs!C:C,"")) -> Doria Pablo Cesar | R56: EFIS | S56: NQN | T56: 1012899 | U56: Operations | V56: WC | AB56: Headcount | AD56: SI
A57: 46266 | B57: 3392838 | C57: Plant Lead Supervisor | D57: EFIS | E57: EFIS | G57: =Table1[[#This Row],[DESCRIPCION_POSICION]] -> Plant Lead Supervisor | H57: DU31341714 | I57: AR-NEUQUÉN | J57: Energy Field Services | K57: Doria Pablo Cesar | L57: EFF-FP0911 | N57: Aguilera Martin Fabian | O57: =VLOOKUP(L57,CECOs!A:B,2,0) -> Operadores SALA EPF | P57: =VLOOKUP(B:B,CECOs!G:I,3,FALSE) -> #N/A | Q57: =IF(_xlfn.XLOOKUP(L57,CECOs!A:A,CECOs!C:C,"")="",K57,_xlfn.XLOOKUP(L57,CECOs!A:A,CECOs!C:C,"")) -> Doria Pablo Cesar | R57: EFIS | S57: NQN | T57: 1012899 | U57: Operations | V57: WC | AB57: Headcount | AD57: SI
A58: 46266 | B58: 3392839 | C58: Plant Lead Supervisor | D58: EFIS | E58: EFIS | G58: =Table1[[#This Row],[DESCRIPCION_POSICION]] -> Plant Lead Supervisor | H58: DU24817522 | I58: AR-NEUQUÉN | J58: Energy Field Services | K58: Doria Pablo Cesar | L58: EFF-FP0911 | N58: Aquin Jorge Alfredo | O58: =VLOOKUP(L58,CECOs!A:B,2,0) -> Operadores SALA EPF | P58: =VLOOKUP(B:B,CECOs!G:I,3,FALSE) -> #N/A | Q58: =IF(_xlfn.XLOOKUP(L58,CECOs!A:A,CECOs!C:C,"")="",K58,_xlfn.XLOOKUP(L58,CECOs!A:A,CECOs!C:C,"")) -> Doria Pablo Cesar | R58: EFIS | S58: NQN | T58: 1012899 | U58: Operations | V58: WC | AB58: Headcount | AD58: SI
A59: 46266 | B59: 3395767 | C59: Plant Sr. Supervisor | D59: EFIS | E59: EFIS | G59: =Table1[[#This Row],[DESCRIPCION_POSICION]] -> Plant Sr. Supervisor | H59: DU27994695 | I59: AR-NEUQUÉN | J59: Energy Field Services | K59: Alcantu Bargna Marcelo Luis | L59: EFR-FN0960 | N59: Acuña Israel Maximiliano | O59: =VLOOKUP(L59,CECOs!A:B,2,0) -> Supervisores Producción | P59: =VLOOKUP(B:B,CECOs!G:I,3,FALSE) -> #N/A | Q59: =IF(_xlfn.XLOOKUP(L59,CECOs!A:A,CECOs!C:C,"")="",K59,_xlfn.XLOOKUP(L59,CECOs!A:A,CECOs!C:C,"")) -> Alcantu Bargna Marcelo Luis | R59: EFIS | S59: NQN | T59: 1012899 | U59: Operations | V59: WC | AB59: Headcount | AD59: SI
A60: 46266 | B60: 3395519 | C60: Production Supervisor | D60: EFIS | E60: EFIS | G60: =Table1[[#This Row],[DESCRIPCION_POSICION]] -> Production Supervisor | H60: DU29861604 | I60: AR-NEUQUÉN | J60: Energy Field Services | K60: Baissac Roberto Enrique | L60: EFR-FN0960 | N60: Mendoza Segundo Rodolfo | O60: =VLOOKUP(L60,CECOs!A:B,2,0) -> Supervisores Producción | P60: =VLOOKUP(B:B,CECOs!G:I,3,FALSE) -> Supervisoroperativo/Producción | Q60: =IF(_xlfn.XLOOKUP(L60,CECOs!A:A,CECOs!C:C,"")="",K60,_xlfn.XLOOKUP(L60,CECOs!A:A,CECOs!C:C,"")) -> Baissac Roberto Enrique | R60: EFIS | S60: NQN | T60: 1016687 | U60: Operations | V60: WC | AB60: Headcount | AD60: SI
A61: 46266 | B61: 3395768 | C61: Production Supervisor | D61: EFIS | E61: EFIS | G61: =Table1[[#This Row],[DESCRIPCION_POSICION]] -> Production Supervisor | H61: DU25113792 | I61: AR-NEUQUÉN | J61: Energy Field Services | K61: Baissac Roberto Enrique | L61: EFR-FN0960 | N61: Rivera Jorge David | O61: =VLOOKUP(L61,CECOs!A:B,2,0) -> Supervisores Producción | P61: =VLOOKUP(B:B,CECOs!G:I,3,FALSE) -> Supervisoroperativo/Producción | Q61: =IF(_xlfn.XLOOKUP(L61,CECOs!A:A,CECOs!C:C,"")="",K61,_xlfn.XLOOKUP(L61,CECOs!A:A,CECOs!C:C,"")) -> Baissac Roberto Enrique | R61: EFIS | S61: NQN | T61: 1016687 | U61: Operations | V61: WC | AB61: Headcount | AD61: APROBADA
A62: 46266 | B62: 3392840 | C62: Integrity Lead Engineer | D62: EFIS | E62: EFIS | G62: =Table1[[#This Row],[DESCRIPCION_POSICION]] -> Integrity Lead Engineer | H62: DU95753737 | I62: AR-NEUQUÉN | J62: Energy Field Services | K62: Diaz Luis Alberto | L62: EFR-FN0931 | N62: Pedraza Romero Ingrith Cristina | O62: =VLOOKUP(L62,CECOs!A:B,2,0) -> Integridad PRR | P62: =VLOOKUP(B:B,CECOs!G:I,3,FALSE) -> Supervisoroperativo/Producción | Q62: =IF(_xlfn.XLOOKUP(L62,CECOs!A:A,CECOs!C:C,"")="",K62,_xlfn.XLOOKUP(L62,CECOs!A:A,CECOs!C:C,"")) -> Diaz Luis Alberto | R62: EFIS | S62: NQN | T62: 1010274 | U62: Maintenance | V62: WC | AB62: Headcount | AD62: SI
A63: 46266 | B63: 3392841 | C63: Maintenance Planning Analyst | D63: EFIS | E63: EFIS | G63: =Table1[[#This Row],[DESCRIPCION_POSICION]] -> Maintenance Planning Analyst | H63: DU32951591 | I63: AR-NEUQUÉN | J63: Energy Field Services | K63: Gulayin Mariana Laura | L63: EFR-FN0932 | N63: Zapata Gustavo Ceferino | O63: =VLOOKUP(L63,CECOs!A:B,2,0) -> Programador PRR | P63: =VLOOKUP(B:B,CECOs!G:I,3,FALSE) -> Personalnooperativo | Q63: =IF(_xlfn.XLOOKUP(L63,CECOs!A:A,CECOs!C:C,"")="",K63,_xlfn.XLOOKUP(L63,CECOs!A:A,CECOs!C:C,"")) -> Gulayin Mariana Laura | R63: EFIS | S63: NQN | T63: 1010274 | U63: Maintenance | V63: WC | AB63: Headcount | AD63: SI
A64: 46266 | B64: 3392842 | C64: Maintenance Planning Analyst | D64: EFIS | E64: EFIS | G64: =Table1[[#This Row],[DESCRIPCION_POSICION]] -> Maintenance Planning Analyst | H64: DU30519172 | I64: AR-NEUQUÉN | J64: Energy Field Services | K64: Cañaveras Adrian Marcelo | L64: EFR-FN0932 | N64: Orozco Luciano Nicolas | O64: =VLOOKUP(L64,CECOs!A:B,2,0) -> Programador PRR | P64: =VLOOKUP(B:B,CECOs!G:I,3,FALSE) -> Personalnooperativo | Q64: =IF(_xlfn.XLOOKUP(L64,CECOs!A:A,CECOs!C:C,"")="",K64,_xlfn.XLOOKUP(L64,CECOs!A:A,CECOs!C:C,"")) -> Cañaveras Adrian Marcelo | R64: EFIS | S64: NQN | T64: 1010274 | U64: Maintenance | V64: WC | AB64: Headcount | AD64: SI
A65: 46266 | B65: 3437844 | C65: Operations Technology Eng. Engineer | D65: EFIS | E65: EFIS | G65: =Table1[[#This Row],[DESCRIPCION_POSICION]] -> Operations Technology Eng. Engineer | I65: AR-NEUQUÉN | J65: Energy Field Services | K65: Forte Federico | L65: EFR-FN0930 | N65: Vacante OT LT2E | O65: =VLOOKUP(L65,CECOs!A:B,2,0) -> OT PRR | P65: =VLOOKUP(B:B,CECOs!G:I,3,FALSE) -> #N/A | Q65: =IF(_xlfn.XLOOKUP(L65,CECOs!A:A,CECOs!C:C,"")="",K65,_xlfn.XLOOKUP(L65,CECOs!A:A,CECOs!C:C,"")) -> Forte Federico | R65: EFIS | S65: NQN | U65: Maintenance | V65: WC | AB65: Headcount | AD65: SI
A66: 46266 | B66: 3408113 | C66: Maintenance Planning Analyst | D66: EFIS | E66: EFIS | G66: =Table1[[#This Row],[DESCRIPCION_POSICION]] -> Maintenance Planning Analyst | H66: DU32246164 | I66: AR-NEUQUÉN | J66: Energy Field Services | K66: Cañaveras Adrian Marcelo | L66: EFR-FN0932 | N66: Corti Ortola Cristian Dario | O66: =VLOOKUP(L66,CECOs!A:B,2,0) -> Programador PRR | P66: =VLOOKUP(B:B,CECOs!G:I,3,FALSE) -> Supervisoroperativo/Producción | Q66: =IF(_xlfn.XLOOKUP(L66,CECOs!A:A,CECOs!C:C,"")="",K66,_xlfn.XLOOKUP(L66,CECOs!A:A,CECOs!C:C,"")) -> Cañaveras Adrian Marcelo | R66: EFIS | S66: NQN | U66: Maintenance | V66: WC | AB66: Headcount
A67: 46266 | B67: 3392844 | C67: Integrity Lead Supervisor | D67: EFIS | E67: EFIS | G67: =Table1[[#This Row],[DESCRIPCION_POSICION]] -> Integrity Lead Supervisor | H67: DU22104238 | I67: AR-NEUQUÉN | J67: Energy Field Services | K67: Diaz Luis Alberto | L67: EFR-FN0931 | N67: Garcia Oscar Ariel | O67: =VLOOKUP(L67,CECOs!A:B,2,0) -> Integridad PRR | P67: =VLOOKUP(B:B,CECOs!G:I,3,FALSE) -> Supervisoroperativo/Producción | Q67: =IF(_xlfn.XLOOKUP(L67,CECOs!A:A,CECOs!C:C,"")="",K67,_xlfn.XLOOKUP(L67,CECOs!A:A,CECOs!C:C,"")) -> Diaz Luis Alberto | R67: EFIS | S67: NQN | T67: 1010274 | U67: Maintenance | V67: WC | AB67: Headcount | AD67: SI
A68: 46266 | B68: 3392845 | C68: Maintenance Sr. Supervisor | D68: EFIS | E68: EFIS | G68: =Table1[[#This Row],[DESCRIPCION_POSICION]] -> Maintenance Sr. Supervisor | H68: DU35834385 | I68: AR-NEUQUÉN | J68: Energy Field Services | K68: Kraemer Nicolás | L68: EFR-FN0910 | N68: Sieben Nicolas | O68: =VLOOKUP(L68,CECOs!A:B,2,0) -> Supervisores Mtto | P68: =VLOOKUP(B:B,CECOs!G:I,3,FALSE) -> Supervisoroperativo/Producción | Q68: =IF(_xlfn.XLOOKUP(L68,CECOs!A:A,CECOs!C:C,"")="",K68,_xlfn.XLOOKUP(L68,CECOs!A:A,CECOs!C:C,"")) -> Kraemer Nicolás | R68: EFIS | S68: NQN | T68: 1010274 | U68: Maintenance | V68: WC | AB68: Headcount | AD68: SI
A69: 46266 | B69: 3392960 | C69: Operador Especializado de Plantas | D69: EFIS | E69: EFIS | G69: =Table1[[#This Row],[DESCRIPCION_POSICION]] -> Operador Especializado de Plantas | H69: DU39129973 | I69: AR-NEUQUÉN | J69: Energy Field Services | K69: Casal Gustavo Daniel | L69: EFF-FP0907 | N69: Canales Vanina Daniela | O69: =VLOOKUP(L69,CECOs!A:B,2,0) -> Oper. Planta Compresión FP | P69: =VLOOKUP(B:B,CECOs!G:I,3,FALSE) -> OperadordeCompresiónPlanta | Q69: =IF(_xlfn.XLOOKUP(L69,CECOs!A:A,CECOs!C:C,"")="",K69,_xlfn.XLOOKUP(L69,CECOs!A:A,CECOs!C:C,"")) -> HUARTE, ESTEBAN | R69: EFIS | S69: NQN | T69: 1016735 | U69: Operations | V69: BC | AB69: Headcount | AD69: SI
A70: 46266 | B70: 3414070 | C70: HSE Lead Supervisor | D70: EFIS | E70: EFIS | G70: =Table1[[#This Row],[DESCRIPCION_POSICION]] -> HSE Lead Supervisor | H70: DU33713574 | I70: AR-NEUQUÉN | J70: Energy Field Services | K70: Martel Maximiliano Jose Tomas | L70: EFF-FN1000 | N70: Lopez Favio Nicolas | O70: =VLOOKUP(L70,CECOs!A:B,2,0) -> PJ TLM | P70: =VLOOKUP(B:B,CECOs!G:I,3,FALSE) -> SupervisoresSAS/OT | Q70: =IF(_xlfn.XLOOKUP(L70,CECOs!A:A,CECOs!C:C,"")="",K70,_xlfn.XLOOKUP(L70,CECOs!A:A,CECOs!C:C,"")) -> Martel Maximiliano Jose Tomas | R70: EFIS | S70: NQN | U70: Health & Safety TLM | V70: WC | AB70: Headcount | AD70: SI
A71: 46266 | B71: 3414075 | C71: Integrity Engineering Engineer | D71: EFIS | E71: EFIS | G71: =Table1[[#This Row],[DESCRIPCION_POSICION]] -> Integrity Engineering Engineer | H71: DU38092352 | I71: AR-NEUQUÉN | J71: Energy Field Services | K71: Segura Alejandro | L71: EFF-FN1000 | N71: Chalop Marcos | O71: =VLOOKUP(L71,CECOs!A:B,2,0) -> PJ TLM | P71: =VLOOKUP(B:B,CECOs!G:I,3,FALSE) -> Supervisoroperativo/Producción | Q71: =IF(_xlfn.XLOOKUP(L71,CECOs!A:A,CECOs!C:C,"")="",K71,_xlfn.XLOOKUP(L71,CECOs!A:A,CECOs!C:C,"")) -> Segura Alejandro | R71: EFIS | S71: NQN | U71: Maintenance TLM | V71: WC | AB71: Headcount | AD71: SI
A72: 46266 | B72: 3437943 | C72: TLM2 Supervisor Mantenimiento | D72: EFIS | E72: EFIS | I72: AR-NEUQUÉN | J72: Energy Field Services | K72: Segura Alejandro | L72: EFF-FN1005 | O72: =VLOOKUP(L72,CECOs!A:B,2,0) -> PJ - TLM 2 | P72: =VLOOKUP(B:B,CECOs!G:I,3,FALSE) -> Supervisoroperativo/Producción | Q72: =IF(_xlfn.XLOOKUP(L72,CECOs!A:A,CECOs!C:C,"")="",K72,_xlfn.XLOOKUP(L72,CECOs!A:A,CECOs!C:C,"")) -> Segura Alejandro | R72: EFIS | S72: NQN | U72: Maintenance TLM | V72: WC
A73: 46266 | B73: 3392843 | C73: O&M Control lead analyst | D73: EFIS | E73: EFIS | G73: =Table1[[#This Row],[DESCRIPCION_POSICION]] -> O&M Control lead analyst | H73: DU26783746 | I73: AR-NEUQUÉN | J73: Energy Field Services | K73: Cañaveras Adrian Marcelo | L73: EFR-FN0932 | N73: Muccela Jose Daniel | O73: =VLOOKUP(L73,CECOs!A:B,2,0) -> Programador PRR | P73: =VLOOKUP(B:B,CECOs!G:I,3,FALSE) -> Personalnooperativo | Q73: =IF(_xlfn.XLOOKUP(L73,CECOs!A:A,CECOs!C:C,"")="",K73,_xlfn.XLOOKUP(L73,CECOs!A:A,CECOs!C:C,"")) -> Cañaveras Adrian Marcelo | R73: EFIS | S73: NQN | T73: 1010274 | U73: Maintenance | V73: WC | AB73: Headcount | AD73: SI
A74: 46266 | B74: 3418975 | C74: Ingresante sin experiencia | D74: EFIS | E74: EFIS | G74: =Table1[[#This Row],[DESCRIPCION_POSICION]] -> Ingresante sin experiencia | I74: AR-NEUQUÉN | J74: Energy Field Services | K74: Cordova Daniela Emiliana | L74: EFF-FP0944 | N74: VACANTE RELEVO VACAS MECÁNICOS | O74: =VLOOKUP(L74,CECOs!A:B,2,0) -> Mecánicos FP | P74: =VLOOKUP(B:B,CECOs!G:I,3,FALSE) -> #N/A | Q74: =IF(_xlfn.XLOOKUP(L74,CECOs!A:A,CECOs!C:C,"")="",K74,_xlfn.XLOOKUP(L74,CECOs!A:A,CECOs!C:C,"")) -> CASAL, GUSTAVO | R74: EFIS | S74: NQN | U74: General Services | V74: BC | AB74: Headcount | AD74: RELEVO VACACIONES
A75: 46266 | B75: 3392822 | C75: HSE Sr. Supervisor | D75: EFIS | E75: EFIS | G75: =Table1[[#This Row],[DESCRIPCION_POSICION]] -> HSE Sr. Supervisor | H75: DU35899723 | I75: AR-NEUQUÉN | J75: Energy Field Services | K75: Vicencio Cecilia Stefania | L75: EFR-FN0945 | N75: Wilton Smith | O75: =VLOOKUP(L75,CECOs!A:B,2,0) -> SAS PRR | P75: =VLOOKUP(B:B,CECOs!G:I,3,FALSE) -> SupervisoresSAS/OT | Q75: =IF(_xlfn.XLOOKUP(L75,CECOs!A:A,CECOs!C:C,"")="",K75,_xlfn.XLOOKUP(L75,CECOs!A:A,CECOs!C:C,"")) -> Vicencio Cecilia Stefania | R75: EFIS | S75: NQN | T75: 1005233 | U75: Health & Safety | V75: WC | AB75: Headcount | AD75: SI
A76: 46266 | B76: 3414077 | C76: TLM Services Coordinator | D76: EFIS | E76: EFIS | G76: =Table1[[#This Row],[DESCRIPCION_POSICION]] -> TLM Services Coordinator | H76: DU41437832 | I76: AR-NEUQUÉN | J76: Energy Field Services | K76: Batallan Pablo Alejandro | L76: EFF-FN1000 | N76: Saffe Julian Agustín | O76: =VLOOKUP(L76,CECOs!A:B,2,0) -> PJ TLM | P76: =VLOOKUP(B:B,CECOs!G:I,3,FALSE) -> FacilitadordeServicios | Q76: =IF(_xlfn.XLOOKUP(L76,CECOs!A:A,CECOs!C:C,"")="",K76,_xlfn.XLOOKUP(L76,CECOs!A:A,CECOs!C:C,"")) -> Batallan Pablo Alejandro | R76: EFIS | S76: NQN | U76: O&M Services | V76: WC | AB76: Headcount | AD76: SI
A77: 46266 | B77: 3424476 | C77: Facilities Operations Lead Supervisor | D77: EFIS | E77: EFIS | G77: =Table1[[#This Row],[DESCRIPCION_POSICION]] -> Facilities Operations Lead Supervisor | H77: DU30824024 | I77: AR-NEUQUÉN | J77: Energy Field Services | K77: Carabajal Marcelo | L77: EFR-FN2000 | N77: Orellana Omar Ismael | O77: =VLOOKUP(L77,CECOs!A:B,2,0) -> Otras especialidades | P77: =VLOOKUP(B:B,CECOs!G:I,3,FALSE) -> Supervisoroperativo/Producción | Q77: =IF(_xlfn.XLOOKUP(L77,CECOs!A:A,CECOs!C:C,"")="",K77,_xlfn.XLOOKUP(L77,CECOs!A:A,CECOs!C:C,"")) -> Carabajal Marcelo | R77: EFIS | S77: NQN | U77: Facilities | V77: WC | AB77: Headcount | AD77: SI
A78: 46266 | B78: 3424477 | C78: Chemical Treatment Lead Supervisor | D78: EFIS | E78: EFIS | G78: =Table1[[#This Row],[DESCRIPCION_POSICION]] -> Chemical Treatment Lead Supervisor | H78: DU29554367 | I78: AR-NEUQUÉN | J78: Energy Field Services | K78: Carreras Natania | L78: EFR-FN2000 | N78: Rodriguez Lucas Matias | O78: =VLOOKUP(L78,CECOs!A:B,2,0) -> Otras especialidades | P78: =VLOOKUP(B:B,CECOs!G:I,3,FALSE) -> 0 | Q78: =IF(_xlfn.XLOOKUP(L78,CECOs!A:A,CECOs!C:C,"")="",K78,_xlfn.XLOOKUP(L78,CECOs!A:A,CECOs!C:C,"")) -> Carreras Natania | R78: EFIS | S78: NQN | U78: Maintenance | V78: WC | AB78: Headcount | AD78: SI
A79: 46266 | B79: 3437611 | C79: General Services Supervisor | D79: EFIS | E79: EFIS | G79: =Table1[[#This Row],[DESCRIPCION_POSICION]] -> General Services Supervisor | H79: DU21389528 | I79: AR-NEUQUÉN | J79: Energy Field Services | K79: Zuluaga Gabriel | L79: EFR-FN2005 | N79: Bartusch Fabian | O79: =VLOOKUP(L79,CECOs!A:B,2,0) -> Supervisores SERGE | P79: =VLOOKUP(B:B,CECOs!G:I,3,FALSE) -> Supervisoroperativo/Producción | Q79: =IF(_xlfn.XLOOKUP(L79,CECOs!A:A,CECOs!C:C,"")="",K79,_xlfn.XLOOKUP(L79,CECOs!A:A,CECOs!C:C,"")) -> Zuluaga Gabriel | R79: EFIS | S79: NQN | U79: General Services | V79: WC | AB79: Headcount | AD79: SI
A80: 46266 | B80: 3437848 | C80: General Services Supervisor | D80: EFIS | E80: EFIS | G80: =Table1[[#This Row],[DESCRIPCION_POSICION]] -> General Services Supervisor | H80: DU39523923 | I80: AR-NEUQUÉN | J80: Energy Field Services | K80: Zuluaga Gabriel | L80: EFR-FN2005 | N80: Martinez Juan Manuel | O80: =VLOOKUP(L80,CECOs!A:B,2,0) -> Supervisores SERGE | P80: =VLOOKUP(B:B,CECOs!G:I,3,FALSE) -> #N/A | Q80: =IF(_xlfn.XLOOKUP(L80,CECOs!A:A,CECOs!C:C,"")="",K80,_xlfn.XLOOKUP(L80,CECOs!A:A,CECOs!C:C,"")) -> Zuluaga Gabriel | R80: EFIS | S80: NQN | U80: General Services | V80: WC | AB80: Headcount | AD80: SI
A81: 46266 | B81: 3437845 | C81: General Services Supervisor | D81: EFIS | E81: EFIS | H81: DU35382241 | I81: AR-NEUQUÉN | J81: Energy Field Services | K81: Zuluaga Gabriel | L81: EFR-FN0941 | N81: Cual Roxana | O81: =VLOOKUP(L81,CECOs!A:B,2,0) -> Indirectos PRR | P81: =VLOOKUP(B:B,CECOs!G:I,3,FALSE) -> #N/A | Q81: =IF(_xlfn.XLOOKUP(L81,CECOs!A:A,CECOs!C:C,"")="",K81,_xlfn.XLOOKUP(L81,CECOs!A:A,CECOs!C:C,"")) -> Zuluaga Gabriel | R81: EFIS | S81: NQN | U81: General Services | V81: WC | AB81: Headcount | AD81: SI
A82: 46266 | B82: 3437876 | C82: Well Services Supervisor | D82: EFIS | E82: EFIS | G82: =Table1[[#This Row],[DESCRIPCION_POSICION]] -> Well Services Supervisor | H82: DU32352316 | I82: AR-NEUQUÉN | J82: Energy Field Services | K82: Buzaglo Sebastian | L82: EFR-FN2007 | N82: Fiore Marco Cesar | O82: =VLOOKUP(L82,CECOs!A:B,2,0) -> Supervisores Well Services | P82: =VLOOKUP(B:B,CECOs!G:I,3,FALSE) -> #N/A | Q82: =IF(_xlfn.XLOOKUP(L82,CECOs!A:A,CECOs!C:C,"")="",K82,_xlfn.XLOOKUP(L82,CECOs!A:A,CECOs!C:C,"")) -> Buzaglo Sebastian | R82: EFIS | S82: NQN | U82: Operations | V82: WC | AB82: Headcount | AD82: SI
A83: 46266 | B83: 3437877 | C83: Well Services Supervisor | D83: EFIS | E83: EFIS | G83: =Table1[[#This Row],[DESCRIPCION_POSICION]] -> Well Services Supervisor | H83: DU21750188 | I83: AR-NEUQUÉN | J83: Energy Field Services | K83: Buzaglo Sebastian | L83: EFR-FN2007 | N83: Lozano Jorge Alberto | O83: =VLOOKUP(L83,CECOs!A:B,2,0) -> Supervisores Well Services | P83: =VLOOKUP(B:B,CECOs!G:I,3,FALSE) -> #N/A | Q83: =IF(_xlfn.XLOOKUP(L83,CECOs!A:A,CECOs!C:C,"")="",K83,_xlfn.XLOOKUP(L83,CECOs!A:A,CECOs!C:C,"")) -> Buzaglo Sebastian | R83: EFIS | S83: NQN | U83: Operations | V83: WC | AB83: Headcount | AD83: SI
A84: 46266 | B84: 3437762 | C84: Sup. Interf y entregas | D84: EFIS | E84: EFIS | I84: AR-NEUQUÉN | J84: Energy Field Services | K84: Crespo Luis | L84: EFF-2E2002 | N84: Vacante Sup. Interf/Entregas | O84: =VLOOKUP(L84,CECOs!A:B,2,0) -> Sup. Interferencias/Entregas LT2E | P84: =VLOOKUP(B:B,CECOs!G:I,3,FALSE) -> Supervisoroperativo/Producción | Q84: =IF(_xlfn.XLOOKUP(L84,CECOs!A:A,CECOs!C:C,"")="",K84,_xlfn.XLOOKUP(L84,CECOs!A:A,CECOs!C:C,"")) -> Crespo Luis
A85: 46266 | B85: 3437763 | C85: Sup. Interf y entregas | D85: EFIS | E85: EFIS | I85: AR-NEUQUÉN | J85: Energy Field Services | K85: Crespo Luis | L85: EFF-2E2002 | N85: Vacante Sup. Interf/Entregas | O85: =VLOOKUP(L85,CECOs!A:B,2,0) -> Sup. Interferencias/Entregas LT2E | P85: =VLOOKUP(B:B,CECOs!G:I,3,FALSE) -> Supervisoroperativo/Producción | Q85: =IF(_xlfn.XLOOKUP(L85,CECOs!A:A,CECOs!C:C,"")="",K85,_xlfn.XLOOKUP(L85,CECOs!A:A,CECOs!C:C,"")) -> Crespo Luis
A86: 46266 | B86: 3437764 | C86: Sup. Interf y entregas | D86: EFIS | E86: EFIS | I86: AR-NEUQUÉN | J86: Energy Field Services | K86: Crespo Luis | L86: EFF-2E2002 | N86: Vacante Sup. Interf/Entregas | O86: =VLOOKUP(L86,CECOs!A:B,2,0) -> Sup. Interferencias/Entregas LT2E | P86: =VLOOKUP(B:B,CECOs!G:I,3,FALSE) -> Supervisoroperativo/Producción | Q86: =IF(_xlfn.XLOOKUP(L86,CECOs!A:A,CECOs!C:C,"")="",K86,_xlfn.XLOOKUP(L86,CECOs!A:A,CECOs!C:C,"")) -> Crespo Luis
A87: 46266 | B87: 3392847 | C87: Operador Especializado Semi Jr. Plantas | D87: EFIS | E87: EFIS | G87: =Table1[[#This Row],[DESCRIPCION_POSICION]] -> Operador Especializado Semi Jr. Plantas | H87: DU31020868 | I87: AR-NEUQUÉN | J87: Energy Field Services | K87: Bechara Lucas Antonio | L87: EFF-LB0908 | N87: Alcaraz Gonzalo Ruben | O87: =VLOOKUP(L87,CECOs!A:B,2,0) -> Oper. PTA LBAS | P87: =VLOOKUP(B:B,CECOs!G:I,3,FALSE) -> OperadordePlantaconvencional | Q87: =IF(_xlfn.XLOOKUP(L87,CECOs!A:A,CECOs!C:C,"")="",K87,_xlfn.XLOOKUP(L87,CECOs!A:A,CECOs!C:C,"")) -> BECHARA, LUCAS ANTONIO | R87: EFIS | S87: NQN | T87: 1016735 | U87: Operations | V87: BC | AB87: Headcount | AD87: SI
A88: 46266 | B88: 3392848 | C88: Operador Principal | D88: EFIS | E88: EFIS | G88: =Table1[[#This Row],[DESCRIPCION_POSICION]] -> Operador Principal | H88: DU27046756 | I88: AR-NEUQUÉN | J88: Energy Field Services | K88: Bechara Lucas Antonio | L88: EFF-LB0908 | N88: Nimbro Andres Alejandro | O88: =VLOOKUP(L88,CECOs!A:B,2,0) -> Oper. PTA LBAS | P88: =VLOOKUP(B:B,CECOs!G:I,3,FALSE) -> OperadordePlantaconvencional | Q88: =IF(_xlfn.XLOOKUP(L88,CECOs!A:A,CECOs!C:C,"")="",K88,_xlfn.XLOOKUP(L88,CECOs!A:A,CECOs!C:C,"")) -> BECHARA, LUCAS ANTONIO | R88: EFIS | S88: NQN | T88: 1016735 | U88: Operations | V88: BC | AB88: Headcount | AD88: SI
A89: 46266 | B89: 3392849 | C89: Operador Principal | D89: EFIS | E89: EFIS | G89: =Table1[[#This Row],[DESCRIPCION_POSICION]] -> Operador Principal | H89: DU26149215 | I89: AR-NEUQUÉN | J89: Energy Field Services | K89: Bechara Lucas Antonio | L89: EFF-LB0908 | N89: Ijurco Jose Luis | O89: =VLOOKUP(L89,CECOs!A:B,2,0) -> Oper. PTA LBAS | P89: =VLOOKUP(B:B,CECOs!G:I,3,FALSE) -> OperadordePlantaconvencional | Q89: =IF(_xlfn.XLOOKUP(L89,CECOs!A:A,CECOs!C:C,"")="",K89,_xlfn.XLOOKUP(L89,CECOs!A:A,CECOs!C:C,"")) -> BECHARA, LUCAS ANTONIO | R89: EFIS | S89: NQN | T89: 1016735 | U89: Operations | V89: BC | AB89: Headcount | AD89: SI
A90: 46266 | B90: 3392850 | C90: Recorredor Especializado | D90: EFIS | E90: EFIS | G90: =Table1[[#This Row],[DESCRIPCION_POSICION]] -> Recorredor Especializado | H90: DU31314191 | I90: AR-NEUQUÉN | J90: Energy Field Services | K90: Bechara Lucas Antonio | L90: EFF-LB0908 | N90: Fuentes Osvaldo Nazareno | O90: =VLOOKUP(L90,CECOs!A:B,2,0) -> Oper. PTA LBAS | P90: =VLOOKUP(B:B,CECOs!G:I,3,FALSE) -> OperadordePlantaconvencional | Q90: =IF(_xlfn.XLOOKUP(L90,CECOs!A:A,CECOs!C:C,"")="",K90,_xlfn.XLOOKUP(L90,CECOs!A:A,CECOs!C:C,"")) -> BECHARA, LUCAS ANTONIO | R90: EFIS | S90: NQN | T90: 1016735 | U90: Operations | V90: BC | AB90: Headcount | AD90: SI
A91: 46266 | B91: 3392851 | C91: Ingresante de Plantas | D91: EFIS | E91: EFIS | G91: =Table1[[#This Row],[DESCRIPCION_POSICION]] -> Ingresante de Plantas | H91: DU42910545 | I91: AR-NEUQUÉN | J91: Energy Field Services | K91: Bechara Lucas Antonio | L91: EFF-LB0908 | N91: Sepulveda Miño Matias Ariel | O91: =VLOOKUP(L91,CECOs!A:B,2,0) -> Oper. PTA LBAS | P91: =VLOOKUP(B:B,CECOs!G:I,3,FALSE) -> OperadordePlantaconvencional | Q91: =IF(_xlfn.XLOOKUP(L91,CECOs!A:A,CECOs!C:C,"")="",K91,_xlfn.XLOOKUP(L91,CECOs!A:A,CECOs!C:C,"")) -> BECHARA, LUCAS ANTONIO | R91: EFIS | S91: NQN | T91: 1016735 | U91: Operations | V91: BC | AB91: Headcount | AD91: SI
A92: 46266 | B92: 3392852 | C92: Ingresante de Plantas | D92: EFIS | E92: EFIS | G92: =Table1[[#This Row],[DESCRIPCION_POSICION]] -> Ingresante de Plantas | H92: DU42518590 | I92: AR-NEUQUÉN | J92: Energy Field Services | K92: Bechara Lucas Antonio | L92: EFF-LB0908 | N92: Abarzua Ruiu Jose Ignacio | O92: =VLOOKUP(L92,CECOs!A:B,2,0) -> Oper. PTA LBAS | P92: =VLOOKUP(B:B,CECOs!G:I,3,FALSE) -> OperadordePlantaconvencional | Q92: =IF(_xlfn.XLOOKUP(L92,CECOs!A:A,CECOs!C:C,"")="",K92,_xlfn.XLOOKUP(L92,CECOs!A:A,CECOs!C:C,"")) -> BECHARA, LUCAS ANTONIO | R92: EFIS | S92: NQN | T92: 1016735 | U92: Operations | V92: BC | AB92: Headcount | AD92: SI
A93: 46266 | B93: 3392853 | C93: Operador Especializado Semi Jr. Plantas | D93: EFIS | E93: EFIS | G93: =Table1[[#This Row],[DESCRIPCION_POSICION]] -> Operador Especializado Semi Jr. Plantas | H93: DU26132258 | I93: AR-NEUQUÉN | J93: Energy Field Services | K93: Bechara Lucas Antonio | L93: EFF-LB0908 | N93: Tapia Dario Andres | O93: =VLOOKUP(L93,CECOs!A:B,2,0) -> Oper. PTA LBAS | P93: =VLOOKUP(B:B,CECOs!G:I,3,FALSE) -> OperadordePlantaconvencional | Q93: =IF(_xlfn.XLOOKUP(L93,CECOs!A:A,CECOs!C:C,"")="",K93,_xlfn.XLOOKUP(L93,CECOs!A:A,CECOs!C:C,"")) -> BECHARA, LUCAS ANTONIO | R93: EFIS | S93: NQN | T93: 1016735 | U93: Operations | V93: BC | AB93: Headcount | AD93: SI
A94: 46266 | B94: 3392854 | C94: Operador Especializado de Plantas | D94: EFIS | E94: EFIS | G94: =Table1[[#This Row],[DESCRIPCION_POSICION]] -> Operador Especializado de Plantas | H94: DU24659935 | I94: AR-NEUQUÉN | J94: Energy Field Services | K94: Bechara Lucas Antonio | L94: EFF-LB0908 | N94: Insulza Sergio Ramon | O94: =VLOOKUP(L94,CECOs!A:B,2,0) -> Oper. PTA LBAS | P94: =VLOOKUP(B:B,CECOs!G:I,3,FALSE) -> OperadordePlantaconvencional | Q94: =IF(_xlfn.XLOOKUP(L94,CECOs!A:A,CECOs!C:C,"")="",K94,_xlfn.XLOOKUP(L94,CECOs!A:A,CECOs!C:C,"")) -> BECHARA, LUCAS ANTONIO | R94: EFIS | S94: NQN | T94: 1016735 | U94: Operations | V94: BC | AB94: Headcount | AD94: SI
A95: 46266 | B95: 3392855 | C95: Operador Especializado de Plantas | D95: EFIS | E95: EFIS | G95: =Table1[[#This Row],[DESCRIPCION_POSICION]] -> Operador Especializado de Plantas | H95: DU33285275 | I95: AR-NEUQUÉN | J95: Energy Field Services | K95: Bechara Lucas Antonio | L95: EFF-LB0908 | N95: Sepulveda Gustavo Andres | O95: =VLOOKUP(L95,CECOs!A:B,2,0) -> Oper. PTA LBAS | P95: =VLOOKUP(B:B,CECOs!G:I,3,FALSE) -> OperadordePlantaconvencional | Q95: =IF(_xlfn.XLOOKUP(L95,CECOs!A:A,CECOs!C:C,"")="",K95,_xlfn.XLOOKUP(L95,CECOs!A:A,CECOs!C:C,"")) -> BECHARA, LUCAS ANTONIO | R95: EFIS | S95: NQN | T95: 1016735 | U95: Operations | V95: BC | AB95: Headcount | AD95: SI
A96: 46266 | B96: 3392856 | C96: Operador Especializado Semi Jr. Plantas | D96: EFIS | E96: EFIS | G96: =Table1[[#This Row],[DESCRIPCION_POSICION]] -> Operador Especializado Semi Jr. Plantas | H96: DU31173446 | I96: AR-NEUQUÉN | J96: Energy Field Services | K96: Bechara Lucas Antonio | L96: EFF-LB0908 | N96: Navarrete Miguel Andres | O96: =VLOOKUP(L96,CECOs!A:B,2,0) -> Oper. PTA LBAS | P96: =VLOOKUP(B:B,CECOs!G:I,3,FALSE) -> OperadordePlantaconvencional | Q96: =IF(_xlfn.XLOOKUP(L96,CECOs!A:A,CECOs!C:C,"")="",K96,_xlfn.XLOOKUP(L96,CECOs!A:A,CECOs!C:C,"")) -> BECHARA, LUCAS ANTONIO | R96: EFIS | S96: NQN | T96: 1016735 | U96: Operations | V96: BC | AB96: Headcount | AD96: SI
A97: 46266 | B97: 3392857 | C97: Ingresante de Plantas | D97: EFIS | E97: EFIS | G97: =Table1[[#This Row],[DESCRIPCION_POSICION]] -> Ingresante de Plantas | H97: DU35492858 | I97: AR-NEUQUÉN | J97: Energy Field Services | K97: Bechara Lucas Antonio | L97: EFF-LB0908 | N97: Fuentes Guillermo Ivan | O97: =VLOOKUP(L97,CECOs!A:B,2,0) -> Oper. PTA LBAS | P97: =VLOOKUP(B:B,CECOs!G:I,3,FALSE) -> OperadordePlantaconvencional | Q97: =IF(_xlfn.XLOOKUP(L97,CECOs!A:A,CECOs!C:C,"")="",K97,_xlfn.XLOOKUP(L97,CECOs!A:A,CECOs!C:C,"")) -> BECHARA, LUCAS ANTONIO | R97: EFIS | S97: NQN | T97: 1016735 | U97: Operations | V97: BC | AB97: Headcount | AD97: SI
A98: 46266 | B98: 3392858 | C98: Ingresante de Plantas | D98: EFIS | E98: EFIS | G98: =Table1[[#This Row],[DESCRIPCION_POSICION]] -> Ingresante de Plantas | H98: DU95988960 | I98: AR-NEUQUÉN | J98: Energy Field Services | K98: Bechara Lucas Antonio | L98: EFF-LB0908 | N98: Medina Chourio Luis Guillermo | O98: =VLOOKUP(L98,CECOs!A:B,2,0) -> Oper. PTA LBAS | P98: =VLOOKUP(B:B,CECOs!G:I,3,FALSE) -> OperadordePlantaconvencional | Q98: =IF(_xlfn.XLOOKUP(L98,CECOs!A:A,CECOs!C:C,"")="",K98,_xlfn.XLOOKUP(L98,CECOs!A:A,CECOs!C:C,"")) -> BECHARA, LUCAS ANTONIO | R98: EFIS | S98: NQN | T98: 1016735 | U98: Operations | V98: BC | AB98: Headcount | AD98: SI
... A136: 46266 | B136: 3392895 | C136: Oficial Sr. de Oficios | D136: EFIS | E136: EFIS | G136: =Table1[[#This Row],[DESCRIPCION_POSICION]] -> Oficial Sr. de Oficios | H136: DU20502072 | I136: AR-NEUQUÉN | J136: Energy Field Services | K136: Bechara Lucas Antonio | L136: EFF-AS0904 | N136: Cardozo Marcos Dante | O136: =VLOOKUP(L136,CECOs!A:B,2,0) -> Tareas Generales Prod SALA | P136: =VLOOKUP(B:B,CECOs!G:I,3,FALSE) -> Tareasgenerales | Q136: =IF(_xlfn.XLOOKUP(L136,CECOs!A:A,CECOs!C:C,"")="",K136,_xlfn.XLOOKUP(L136,CECOs!A:A,CECOs!C:C,"")) -> BECHARA, LUCAS ANTONIO | R136: EFIS | S136: NQN | T136: 1016735 | U136: Operations | V136: BC | AB136: Headcount | AD136: SI
A137: 46266 | B137: 3392897 | C137: Ayudante de Plantas | D137: EFIS | E137: EFIS | G137: =Table1[[#This Row],[DESCRIPCION_POSICION]] -> Ayudante de Plantas | I137: AR-NEUQUÉN | J137: Energy Field Services | K137: Bechara Lucas Antonio | L137: EFF-AS0904 | N137: VACANTE PARIS (ATG) | O137: =VLOOKUP(L137,CECOs!A:B,2,0) -> Tareas Generales Prod SALA | P137: =VLOOKUP(B:B,CECOs!G:I,3,FALSE) -> Tareasgenerales | Q137: =IF(_xlfn.XLOOKUP(L137,CECOs!A:A,CECOs!C:C,"")="",K137,_xlfn.XLOOKUP(L137,CECOs!A:A,CECOs!C:C,"")) -> BECHARA, LUCAS ANTONIO | R137: EFIS | S137: NQN | T137: 1016735 | U137: Operations | V137: BC | AB137: Headcount | AD137: SI
...

Sheet REFERENCIAS 
A1: REFERENCIAS COLORES
A2: VACANTES
A3: MOVIMIENTOS
A4: INGRESOS

Sheet CECOs
A1: Ceco EFIS Específico | B1: Órden EFIS | C1: Facilitador | G1: S | H1: Descripción Posición | I1: Clasificación
A2: EFF-FP0901 | B2: Oper campo FP | C2: HUARTE, ESTEBAN | G2: 3392801 | H2: PRR Facilitadores FORT | I2: FacilitadordeServicios
A3: EFF-FP0902 | B3: Oper Well Services FP | C3: MACIAS, OSCAR / SAFFE, JULIAN | G3: 3392802 | H3: PRR Facilitadores FORT | I3: FacilitadordeServicios
A4: EFF-FP0903 | B4: Almacenamiento de Agua FP | C4: HUARTE, ESTEBAN | G4: 3392803 | H4: PRR Facilitadores FORT | I4: FacilitadordeServicios
A5: EFF-FP0905 | B5: Oper. LTS FP | C5: HUARTE, ESTEBAN | G5: 3392804 | H5: Facilitador Well Services - FP | I5: FacilitadordeServicios
A6: EFF-FP0906 | B6: Oper. EPF FP | C6: HUARTE, ESTEBAN | G6: 3392805 | H6: PRR Facilitadores CONV - Facilitador LBAS | I6: FacilitadordeServicios
A7: EFF-FP0911 | B7: Operadores SALA EPF | G7: 3392806 | H7: PRR Facilitadores FORT | I7: FacilitadordeServicios
A8: EFF-FP0907 | B8: Oper. Planta Compresión FP | C8: HUARTE, ESTEBAN | G8: 3392808 | H8: PRR Facilitadores FORT | I8: FacilitadordeServicios
A9: EFF-FP0908 | B9: Oper. PTA FP | C9: HUARTE, ESTEBAN | G9: 3392811 | H9: Indirectos PRR - RRHH | I9: Personalnooperativo
A10: EFF-FP0909 | B10: Tareas Generales Planta FP | C10: HUARTE, ESTEBAN | G10: 3392812 | H10: Indirectos PRR - RRHH | I10: Personalnooperativo
A11: EFF-FP0921 | B11: Mtto Mecánico FP | C11: CORDOVA, DANIELA / ALTAMIRANDA, LEANDRO | G11: 3392813 | H11: Indirectos PRR - RRLL | I11: Personalnooperativo
A12: EFF-FP0922 | B12: Mtto Eléctrico FP | C12: CORDOVA, DANIELA / ALTAMIRANDA, LEANDRO | G12: 3392814 | H12: Indirectos PRR - Calidad | I12: Personalnooperativo
A13: EFF-FP0923 | B13: Mtto Instrumentos FP | C13: CORDOVA, DANIELA / ALTAMIRANDA, LEANDRO | G13: 3392815 | H13: Indirectos PRR - SERGE Sup. Flota | I13: Supervisoroperativo/Producción
A14: EFF-FP0924 | B14: Compresión FP | C14: CORDOVA, DANIELA / ALTAMIRANDA, LEANDRO | G14: 3392816 | H14: SAS PRR | I14: SupervisoresSAS/OT
A15: EFF-FP0925 | B15: Soldadura FP | C15: CORDOVA, DANIELA / ALTAMIRANDA, LEANDRO | G15: 3392817 | H15: SAS PRR | I15: SupervisoresSAS/OT
A16: EFF-FP0926 | B16: Tareas Generales Mtto FP | C16: CORDOVA, DANIELA / ALTAMIRANDA, LEANDRO | G16: 3392818 | H16: SAS PRR | I16: SupervisoresSAS/OT
A17: EFF-FP0927 | B17: Asistencia a Planta FP | C17: CORDOVA, DANIELA / ALTAMIRANDA, LEANDRO | G17: 3392819 | H17: SAS PRR | I17: SupervisoresSAS/OT
A18: EFF-FP0928 | B18: Engrase FP | C18: CORDOVA, DANIELA / ALTAMIRANDA, LEANDRO | G18: 3392820 | H18: SAS PRR | I18: SupervisoresSAS/OT
A19: EFF-FP0929 | B19: T. Grales Serge Fp | C19: CASAL, GUSTAVO | G19: 3392821 | H19: SAS PRR | I19: SupervisoresSAS/OT
A20: EFF-2E0929 | B20: T. Grales Serge LT2E | C20: MERCADO, MAURICIO / FREDES, RUBEN | G20: 3392822 | H20: SAS PRR | I20: SupervisoresSAS/OT
A21: EFF-FP0930 | B21: OT FP | G21: 3395760 | H21: SAS PRR | I21: Personalnooperativo
A22: EFF-FP0931 | B22: Integridad FP | G22: 3395761 | H22: SAS PRR | I22: Personalnooperativo
A23: EFF-FP0932 | B23: Programador FP | G23: 3392823 | H23: SAS PRR | I23: SupervisoresSAS/OT
A24: EFF-FP0942 | B24: Aux. Almacén FP | C24: CASAL, GUSTAVO | G24: 3392824 | H24: SAS PRR | I24: Personalnooperativo
A25: EFF-2E0942 | B25: Aux. Almacén LT2E | C25: MERCADO, MAURICIO / FREDES, RUBEN | G25: 3392825 | H25: Mantenimiento - OT PRR - PRR FORT | I25: SupervisoresSAS/OT
A26: EFF-FP0943 | B26: Chofer FP | C26: CASAL, GUSTAVO | G26: 3392826 | H26: Mantenimiento - OT PRR - PRR FORT | I26: SupervisoresSAS/OT
A27: EFF-FP0944 | B27: Mecánicos FP | C27: CASAL, GUSTAVO | G27: 3392827 | H27: Mantenimiento - OT PRR - PRR FORT | I27: SupervisoresSAS/OT
A28: EFF-FP0945 | B28: SAS FP | G28: 3392828 | H28: Mantenimiento - OT PRR - PRR FORT | I28: SupervisoresSAS/OT
A29: EFF-LB0901 | B29: Oper campo LBAS | C29: BECHARA, LUCAS ANTONIO | G29: 3392829 | H29: Mantenimiento - OT PRR - PRR FORT | I29: SupervisoresSAS/OT
A30: EFF-LB0904 | B30: Tareas Generales Prod LBAS | C30: BECHARA, LUCAS ANTONIO | G30: 3392830 | H30: Mantenimiento - OT PRR - PRR FORT | I30: SupervisoresSAS/OT
A31: EFF-LB0908 | B31: Oper. PTA LBAS | C31: BECHARA, LUCAS ANTONIO | G31: 3392831 | H31: Mantenimiento - OT PRR - PRR LBAS/ASAL | I31: SupervisoresSAS/OT
A32: EFF-LB0921 | B32: Mtto Mecánico LBAS | C32: BECHARA, LUCAS ANTONIO | G32: 3392834 | H32: PRR Supervisores Mtto FP | I32: Supervisoroperativo/Producción
A33: EFF-LB0922 | B33: Mtto Eléctrico LBAS | C33: BECHARA, LUCAS ANTONIO | G33: 3392835 | H33: PRR Supervisores Mtto FP | I33: Supervisoroperativo/Producción
A34: EFF-LB0923 | B34: Mtto Instrumentos LBAS | C34: BECHARA, LUCAS ANTONIO | G34: 3401242 | H34: PRR Supervisores Mtto FP | I34: Supervisoroperativo/Producción
A35: EFF-LB0925 | B35: Soldadura LBAS | C35: BECHARA, LUCAS ANTONIO | G35: 3401243 | H35: PRR Supervisores Mtto FP | I35: Supervisoroperativo/Producción
A36: EFF-LB0929 | B36: T. Grales Serge LBAS | G36: 3395519 | H36: Producción - PRR Supervisores Producción - PRR - Sup. Producción LT1N | I36: Supervisoroperativo/Producción
A37: EFF-LB0930 | B37: OT LBAS | G37: 3395768 | H37: Producción - PRR Supervisores Producción - PRR - Sup. Producción LT1N | I37: Supervisoroperativo/Producción
A38: EFF-LB0931 | B38: Integridad LBAS | G38: 3392840 | H38: Mantenimiento - Integridad PRR - PRR FP | I38: Supervisoroperativo/Producción
A39: EFF-LB0932 | B39: Programador LBAS | G39: 3392841 | H39: Mantenimiento - Programador PRR - PRR FP | I39: Personalnooperativo
A40: EFF-LB0942 | B40: Aux. Almacén LBAS | C40: BECHARA, LUCAS ANTONIO | G40: 3392842 | H40: Mantenimiento - Programador PRR - PRR FP | I40: Personalnooperativo
A41: EFF-LB0945 | B41: SAS LBAS | G41: 3392843 | H41: Mantenimiento - Programador PRR - PRR LBAS/ASAL | I41: Personalnooperativo
A42: EFF-AS0901 | B42: Oper campo SALA | C42: BECHARA, LUCAS ANTONIO | G42: 3392844 | H42: Mantenimiento - Integridad PRR - PRR FP | I42: Supervisoroperativo/Producción
A43: EFF-AS0904 | B43: Tareas Generales Prod SALA | C43: BECHARA, LUCAS ANTONIO | G43: 3392845 | H43: PRR Supervisores Mtto LBAS | I43: Supervisoroperativo/Producción
A44: EFF-AS0908 | B44: Oper. PTA SALA | C44: BECHARA, LUCAS ANTONIO | G44: 3392846 | H44: Mantenimiento - Integridad PRR - PRR LB | I44: Supervisoroperativo/Producción
A45: EFF-AS0921 | B45: Mtto Mecánico SALA | C45: BECHARA, LUCAS ANTONIO | G45: 3392847 | H45: Plantas - Oper. PTA LBAS | I45: OperadordePlantaconvencional
A46: EFF-AS0922 | B46: Mtto Eléctrico SALA | C46: BECHARA, LUCAS ANTONIO | G46: 3392848 | H46: Plantas - Oper. PTA LBAS | I46: OperadordePlantaconvencional
A47: EFF-AS0923 | B47: Mtto Instrumentos SALA | C47: BECHARA, LUCAS ANTONIO | G47: 3392849 | H47: Plantas - Oper. PTA LBAS | I47: OperadordePlantaconvencional
A48: EFF-AS0925 | B48: Soldadura SALA | C48: BECHARA, LUCAS ANTONIO | G48: 3392850 | H48: Plantas - Oper. PTA LBAS | I48: OperadordePlantaconvencional
A49: EFF-AS0929 | B49: T. Grales Serge SALA | C49: BECHARA, LUCAS ANTONIO | G49: 3392851 | H49: Plantas - Oper. PTA LBAS | I49: OperadordePlantaconvencional
A50: EFF-AS0930 | B50: OT SALA | G50: 3392852 | H50: Plantas - Oper. PTA LBAS | I50: OperadordePlantaconvencional
A51: EFF-AS0931 | B51: Integridad SALA | G51: 3392853 | H51: Plantas - Oper. PTA LBAS | I51: OperadordePlantaconvencional
A52: EFF-AS0932 | B52: Programador SALA | G52: 3392854 | H52: Plantas - Oper. PTA LBAS | I52: OperadordePlantaconvencional
A53: EFF-AS0942 | B53: Aux. Almacén SALA | C53: BECHARA, LUCAS ANTONIO | G53: 3392855 | H53: Plantas - Oper. PTA LBAS | I53: OperadordePlantaconvencional
A54: EFF-AS0945 | B54: SAS SALA | G54: 3392856 | H54: Plantas - Oper. PTA LBAS | I54: OperadordePlantaconvencional
A55: EFF-2E0901 | B55: Oper campo LT2E | C55: MERCADO, MAURICIO / FREDES, RUBEN | G55: 3392857 | H55: Plantas - Oper. PTA LBAS | I55: OperadordePlantaconvencional
A56: EFF-2E0943 | B56: Chofer LT2E | C56: MERCADO, MAURICIO / FREDES, RUBEN | G56: 3392858 | H56: Plantas - Oper. PTA LBAS | I56: OperadordePlantaconvencional
A57: EFF-2E0945 | B57: SAS LT2E | G57: 3392859 | H57: Plantas - Oper. PTA LBAS | I57: OperadordePlantaconvencional
A58: EFF-2E0932 | B58: Programador LT2E | G58: 3392860 | H58: Plantas - Tareas Generales Prod LBAS | I58: Relevomantenimiento
A59: EFF-1N0901 | B59: Oper campo LT1N | C59: MERCADO, MAURICIO / FREDES, RUBEN | G59: 3392861 | H59: Plantas - Tareas Generales Prod LBAS | I59: TareasgeneralesLBAS
A60: EFF-2E0930 | B60: OT LT2E | G60: 3392862 | H60: T. Grales Serge PRR | I60: Serviciosgenerales
A61: EFF-FN1000 | B61: PJ TLM | G61: 3392863 | H61: Almacenes - Aux. Almacén FP | I61: AlmacenNoconvencional
A62: EFF-FN1001 | B62: Operadores TLM | C62: MACIAS, OSCAR / SAFFE, JULIAN | G62: 3392864 | H62: Almacenes - Aux. Almacén - Relevo FP | I62: AlmacenNoconvencional
A63: EFF-FN1002 | B63: Mantenimiento TLM | C63: MACIAS, OSCAR / SAFFE, JULIAN | G63: 3392865 | H63: Producción - Oper campo LBAS | I63: OperadordeCampo
A64: EFF-FN1003 | B64: Mecánicos de flota TLM | C64: CASAL, GUSTAVO | G64: 3392866 | H64: Producción - Oper campo LBAS | I64: OperadordeCampo
A65: EFF-FN1004 | B65: Relevos TLM | C65: MACIAS, OSCAR / SAFFE, JULIAN | G65: 3392867 | H65: Producción - Oper campo LBAS | I65: OperadordeCampo
A66: EFR-FN0929 | B66: T. Grales Serge PRR | C66: BECHARA, LUCAS ANTONIO | G66: 3392868 | H66: Producción - Oper campo LBAS | I66: OperadordeCampo
A67: EFR-FN0930 | B67: OT PRR | G67: 3392869 | H67: Producción - Oper campo LBAS | I67: OperadordeCampo
A68: EFR-FN0931 | B68: Integridad PRR | G68: 3392870 | H68: Producción - Oper campo LBAS | I68: OperadordeCampo
A69: EFR-FN0932 | B69: Programador PRR | G69: 3392871 | H69: Producción - Oper campo LBAS | I69: OperadordeCampo
A70: EFR-FN0945 | B70: SAS PRR | G70: 3392872 | H70: Producción - Oper campo LBAS | I70: OperadordeCampo
A71: EFR-FN0941 | B71: Indirectos PRR | G71: 3392873 | H71: Producción - Oper campo LBAS | I71: OperadordeCampo
A72: EFR-FN0900 | B72: Facilitadores CONV | G72: 3392874 | H72: Producción - Oper campo LBAS | I72: OperadordeCampo
A73: EFR-FN0920 | B73: Facilitadores FP | G73: 3392875 | H73: Producción - Oper campo LBAS | I73: OperadordeCampo
A74: EFR-FN0910 | B74: Supervisores Mtto | G74: 3392876 | H74: Mantenimiento - Mtto Instrumentos LBAS | I74: InstrumentistaConvencional
A75: EFR-FN0960 | B75: Supervisores Producción | G75: 3392877 | H75: Mantenimiento - Mtto Instrumentos LBAS | I75: InstrumentistaConvencional
A76: FPF-FN0940 | B76: Sueldos TECPE | G76: 3392878 | H76: Mantenimiento - Mtto Eléctrico LBAS | I76: EléctricoConvencional
A77: EFF-FP0934 | B77: Mtto Well Services FP | C77: MACIAS, OSCAR / SAFFE, JULIAN | G77: 3392879 | H77: Mantenimiento - Mtto Eléctrico LBAS | I77: EléctricoConvencional
A78: EFF-FP0935 | B78: Montaje y Soldadura FP | C78: CASAL, GUSTAVO | G78: 3392880 | H78: Mantenimiento - Mtto Mecánico LBAS | I78: MecánicosLBAS
A79: EFF-FN2000 | B79: Otras especialidades | G79: 3392881 | H79: Mantenimiento - Mtto Mecánico LBAS | I79: MecánicosLBAS
A80: EFR-2E0970 | B80: Facilitadores LT2E | G80: 3392882 | H80: Mantenimiento - Mtto Mecánico LBAS | I80: Relevomantenimiento
A81: EFF-2E0902 | B81: Well Testing LT2E | G81: 3392883 | H81: Mantenimiento - Soldadura LBAS | I81: Cuadrillasoldadura-CañistaO&M
A82: EFF-2E0903 | B82: Almacenamiento de Agua LT2E | C82: MERCADO, MAURICIO / FREDES, RUBEN | G82: 3392884 | H82: Mantenimiento - Soldadura LBAS | I82: Cuadrillasoldadura-SoldadorO&M
A83: EFF-2E0908 | B83: Oper. PTA LT2E | C83: MERCADO, MAURICIO / FREDES, RUBEN | G83: 3392885 | H83: Mantenimiento - Soldadura LBAS | I83: Cuadrillasoldadura-SoldadorO&M
A84: EFF-2E0909 | B84: Tareas Generales Planta LT2E | C84: MERCADO, MAURICIO / FREDES, RUBEN | G84: 3393252 | H84: Mantenimiento - Soldadura FP | I84: Cuadrillasoldadura-SoldadorO&M
A85: EFF-2E0912 | B85: Oper PTC | C85: MERCADO, MAURICIO / FREDES, RUBEN | G85: 3392886 | H85: Plantas - Oper. PTA SALA - SALA | I85: OperadordePlantaconvencional
A86: EFF-2E0913 | B86: Oper PTG | C86: MERCADO, MAURICIO / FREDES, RUBEN | G86: 3392887 | H86: Plantas - Oper. PTA SALA - SALA | I86: OperadordePlantaconvencional
A87: EFF-2E0921 | B87: Mtto Mecánico LT2E | C87: MERCADO, MAURICIO / FREDES, RUBEN | G87: 3392888 | H87: Plantas - Oper. PTA SALA - SALA | I87: OperadordePlantaconvencional
A88: EFF-2E0922 | B88: Mtto Eléctrico LT2E | C88: MERCADO, MAURICIO / FREDES, RUBEN | G88: 3392889 | H88: Plantas - Oper. PTA SALA - SALA | I88: OperadordePlantaconvencional
A89: EFF-2E0923 | B89: Instrumentistas LT2E | C89: MERCADO, MAURICIO / FREDES, RUBEN | G89: 3392890 | H89: Plantas - Oper. PTA SALA - SALA | I89: OperadordePlantaconvencional
A90: EFF-2E0925 | B90: Soldadura LT2E | C90: MERCADO, MAURICIO / FREDES, RUBEN | G90: 3392891 | H90: Plantas - Oper. PTA SALA - SALA | I90: OperadordePlantaconvencional
A91: EFF-2E0926 | B91: Tareas Generales Mtto LT2E | C91: MERCADO, MAURICIO / FREDES, RUBEN | G91: 3392892 | H91: Plantas - Oper. PTA SALA - SALA | I91: OperadordePlantaconvencional
A92: EFF-2E0928 | B92: Engrase LT2E | C92: MERCADO, MAURICIO / FREDES, RUBEN | G92: 3392893 | H92: Plantas - Oper. PTA SALA - SALA | I92: OperadordePlantaconvencional
A93: EFF-2E0934 | B93: Mtto Well Services LT2E | C93: MACIAS, OSCAR / SAFFE, JULIAN | G93: 3392894 | H93: Producción - Oper campo SALA - SALA | I93: OperadordeCampo
... A98: EFF-2E0944 | B98: Mecánicos Flota LT2E | C98: MERCADO, MAURICIO / FREDES, RUBEN | G98: 3392901 | H98: Producción - Oper campo SALA - SALA | I98: OperadordeCampo
A99: EFF-FP2000 | B99: Ing. Seg. Procesos FDP | G99: 3392902 | H99: Producción - Oper campo SALA - SALA | I99: OperadordeCampo
A100: EFF-2E2000 | B100: Quimicos/integridad LT2E | G100: 3392903 | H100: Producción - Oper campo SALA - SALA | I100: OperadordeCampo
A101: EFR-FN2000 | B101: Otras especialidades | G101: 3392904 | H101: Producción - Oper campo SALA - SALA | I101: OperadordeCampo
A102: EFF-FP2001 | B102: Supervisor Qcos | G102: 3392905 | H102: Producción - Oper campo SALA - SALA | I102: OperadordeCampo
A103: EFF-FP2003 | B103: Supervisores Calidad | G103: 3392906 | H103: Producción - Oper campo SALA - SALA | I103: OperadordeCampo
A104: EFF-FP2004 | B104: Supervisores Facilidades | G104: 3392907 | H104: Producción - Oper campo SALA - SALA | I104: OperadordeCampo
...

Sheet Sheet1
A3: Etiquetas de fila | B3: Count of DESCRIPCION_PERSONA
A4: Bechara Lucas Antonio | B4: 76
A5: Aux. Almacén LBAS | B5: 1
A6: Aux. Almacén SALA | B6: 1
A7: Mtto Eléctrico LBAS | B7: 2
A8: Mtto Eléctrico SALA | B8: 3
A9: Mtto Instrumentos LBAS | B9: 2
A10: Mtto Instrumentos SALA | B10: 2
A11: Mtto Mecánico LBAS | B11: 3
A12: Mtto Mecánico SALA | B12: 2
A13: Oper campo LBAS | B13: 11
A14: Oper campo SALA | B14: 17
A15: Oper. PTA LBAS | B15: 13
... A55: Total general | B55: 256

Sheet Qs
A1: WC_BC | B1: (Todas)
A3: Count of PERSONA | B3: Etiquetas de columna
A4: Etiquetas de fila | B4: SI | C4: RELEVO VACACIONES | D4: PF 3 meses | E4: Total general
A5: EFF-FP0901 | B5: 18 | E5: 18
A6: Abarzua Mario Hernan | B6: 1 | E6: 1
A7: Astorga Sergio Edgardo | B7: 1 | E7: 1
A8: Bunajul Emiliano Miguel | B8: 1 | E8: 1
A9: Castro Marcos Aurelio | B9: 1 | E9: 1
A10: Donnini Julio Samuel | B10: 1 | E10: 1
A11: Fonseca Lucas Ivan | B11: 1 | E11: 1
A12: Fuentes Roberto Alejandro | B12: 1 | E12: 1
A13: Garce Mauro Xavier | B13: 1 | E13: 1
A14: Gonzalez Perez Andy Paolo | B14: 1 | E14: 1
A15: Gutierrez Oscar Javier | B15: 1 | E15: 1
A16: Hernandez Ramon Horacio | B16: 1 | E16: 1
... A31: Fuentes Lopez Gaston Emiliano | B31: 1 | E31: 1
A32: Kochereschuk Brian Alexis
A33: Lopez Ramiro Alejandro Antonio
A34: Garcia Leandro Erik Maximiliano
A35: Prieto Hugo Ernesto
A36: Silva Diego Mauro
A37: Alderete Pablo
A38: Matus Mondaca Gustavo Adan
A39: Firpo Gabriel Cesar Ivan
A40: Canales Ruiz Axel Agustín
A41: Jesus Carlos Abraham
A42: Diaz Jonatan Nicolas
A43: Rosas Diego Nicolas
A44: Cardenas Cristian Ivan
A45: EFF-FP0903 | B45: 5 | E45: 5
A46: Candia Matias Emanuel | B46: 1 | E46: 1
A47: Gallas Fernando Ezequiel | B47: 1 | E47: 1
A48: Gonzalez Jorge Omar | B48: 1 | E48: 1
A49: Pineda Jorge Oscar | B49: 1 | E49: 1
A50: Sandoval Marcos Alexis Aryon | B50: 1 | E50: 1
A51: EFF-FP0905 | B51: 10 | E51: 10
A52: Cordoba Diego Gerardo | B52: 1 | E52: 1
A53: Estelrrig Miguel Horacio | B53: 1 | E53: 1
A54: Figueroa Pablo Emanuel | B54: 1 | E54: 1
A55: Huenchullan Jose Enrique | B55: 1 | E55: 1
A56: Lara Oscar Alexis | B56: 1 | E56: 1
... A61: Velasquez Rodrigo Martin | B61: 1 | E61: 1
A62: Romero Tobias Juan Cruz
A63: Vacante Trainee genera
A64: vacante relevo vacaciones plantas FP
A65: Valenzuela Wachnowski Juan Daniel
A66: EFF-FP0906 | B66: 8 | E66: 8
A67: Castillo Marion Itati | B67: 1 | E67: 1
A68: Contreras Nahir Kalis | B68: 1 | E68: 1
A69: Montecino Miguel Angel | B69: 1 | E69: 1
A70: Nicloux Grecia Macarena | B70: 1 | E70: 1
A71: Oehmcke Dante Guillermo | B71: 1 | E71: 1
A72: Perea Maximiliano Exequiel
A73: Pereyra Gianluca | B73: 1 | E73: 1
A74: Tortosa Garcia Luis Aricelio | B74: 1 | E74: 1
A75: Ventura Montoya Fernando Jose | B75: 1 | E75: 1
A76: EFF-FP0907 | B76: 8 | E76: 8
A77: Canales Vanina Daniela | B77: 1 | E77: 1
A78: Della Paolera Sebastian | B78: 1 | E78: 1
A79: Garcia Pacek German Daniel | B79: 1 | E79: 1
A80: Montenegro Cesar Francisco | B80: 1 | E80: 1
A81: Olmedo Nahuel Fernando | B81: 1 | E81: 1
A82: Querci Damian Agustin | B82: 1 | E82: 1
A83: Sepulveda Victor Francisco | B83: 1 | E83: 1
A84: Vega Obreque Yoel Ezequiel
A85: Villagra Eduardo Rogelio | B85: 1 | E85: 1
A86: Centeno Victor Emilio
A87: Floridio Alana David
A88: Gutierrez Tomas Agustin
A89: Magliotto Pablo Andres
A90: Videla Lucas Patricio
A91: EFF-FP0908 | B91: 13 | E91: 13
A92: Almonacid Santiago Rodrigo | B92: 1 | E92: 1
A93: Carrasco Yohana Yanina Belen | B93: 1 | E93: 1
A94: Lemos Gustavo Damian | B94: 1 | E94: 1
A95: Otarola Alfredo Gustavo | B95: 1 | E95: 1
A96: Rivolta Magali Soledad | B96: 1 | E96: 1
A97: Sandoval Chandia Ramon Rodrigo | B97: 1 | E97: 1
A98: Sanhueza Ramiro Exequiel | B98: 1 | E98: 1
A99: Zapata Elias | B99: 1 | E99: 1
A100: Sanchez Millarin Claudio | B100: 1 | E100: 1
A101: (en blanco)
A102: Puel Luciano Nazaret | B102: 1 | E102: 1
A103: Fernandez Abel Nicolás | B103: 1 | E103: 1
A104: Marchand Marcos | B104: 1 | E104: 1
A105: Barros Tobares Tomas | B105: 1 | E105: 1
A106: Corvalan Valentin
A107: Canales Laura Karina
A108: EFF-FP0909 | B108: 2 | E108: 2
A109: Montesino Matias Eleazar
A110: Valenzuela Juan Carlos David | B110: 1 | E110: 1
A111: Parada Matias Gonzalo | B111: 1 | E111: 1
A112: Encina Lucas Maximiliano
A113: vacante cuadrilla temporal
A114: EFF-FP0921 | B114: 9 | E114: 9
A115: Chanqueo Guillermo Lautaro | B115: 1 | E115: 1
A116: Lopez Ezequiel Sebastian | B116: 1 | E116: 1
A117: Muñoz Gustavo Alberto | B117: 1 | E117: 1
A118: Nava Eduardo David | B118: 1 | E118: 1
A119: Sanchez Alcaraz Rodrigo Ezequiel | B119: 1 | E119: 1
...

Sheet Mes
A1: {=CELL("filename",A1)} -> #VALUE!
A2: =DATE( RIGHT(MID(MID(A1,FIND("[",A1)+1,FIND("]",A1)-FIND("[",A1)-1),SEARCH(".xl",MID(A1,FIND("[",A1)+1,FIND("]",A1)-FIND("[",A1)-1))-7,7),4), LEFT(MID(MID(A1,FIND("[",A1)+1,FIND("]",A1)-FIND("[",A1)-1),SEARCH(".xl",MID(A1,FIND("[",A1)+1,FIND("]",A1)-FIND("[",A1)-1))-7,7),2), 1 ) -> #VALUE!

Sheet SOLAPAMIENTO
B1: POS | C1: Apellido | D1: Nombre | E1: CECO | F1: DNI | G1: COMENTARIOS
A2: 45798 | B2: 3392969 | G2: revisar si es una pos real/vacante?
A3: 45798 | B3: 3393023 | C3: De la Fuente | G3: revisar si es una pos real/vacante?
G4: ELIMINADA EN JULIO (POR CAMBIOS DE CONV Y ROTACIÓN DE CANCINO A LBAS)
A9: # | B9: ID Posición | C9: Posición | D9: CECO | E9: Dirección | F9: Agrupador Gerencia | G9: Gerencia Jefatura | H9: Operación | I9: Jefe
A10: 1 | B10: 3392814 | C10: Vacante - Quality Analyst | D10: EFR-FN0941 | E10: Operations & Argentina Conventional | F10: Quality | G10: Quality | H10: Neuquén - EFiS | I10: Seri Walter Omar | J10: =VLOOKUP(B10,#REF!,13,0) -> #REF!
A11: 1 | B11: 3393032 | C11: Vacante - Oficial de Oficios | D11: EFF-FP0921 | E11: Cuenca Neuquina & Vaca Muerta | F11: Operations & Engineering | G11: Mantainance Services | H11: Neuquén - EFiS | I11: Lemos Sergio Dario | J11: =VLOOKUP(B11,#REF!,13,0) -> #REF!
A12: 1 | B12: 3392884 | C12: Vacante - Oficial Sr. de Oficios | D12: EFF-LB0925 | E12: Cuenca Neuquina & Vaca Muerta | F12: Operations & Engineering | G12: Mantainance Services | H12: Neuquén - EFiS | I12: Altamiranda Leandro Damian | J12: =VLOOKUP(B12,#REF!,13,0) -> #REF!
A13: 1 | B13: 3393037 | C13: Vacante - Operador Principal de Cuadrilla | D13: EFF-FP0925 | E13: Cuenca Neuquina & Vaca Muerta | F13: Operations & Engineering | G13: Mantainance Services | H13: Neuquén - EFiS | I13: Lemos Sergio Dario | J13: =VLOOKUP(B13,#REF!,13,0) -> #REF!
A14: 1 | B14: 3392953 | C14: Licencia - Carrasco | D14: EFF-FP0908 | E14: Cuenca Neuquina & Vaca Muerta | F14: Operations & Engineering | G14: Operations Services | H14: Neuquén - EFiS | I14: Bechara Lucas Antonio | J14: =VLOOKUP(B14,#REF!,13,0) -> #REF!
A15: 1 | B15: 3392948 | C15: Licencia - Nicloux | D15: EFF-FP0908 | E15: Cuenca Neuquina & Vaca Muerta | F15: Operations & Engineering | G15: Operations Services | H15: Neuquén - EFiS | I15: Bechara Lucas Antonio | J15: =VLOOKUP(B15,#REF!,13,0) -> #REF!
A16: 1 | B16: 3392986 | C16: Vacante - Recorredor Especializado | D16: EFF-FP0901 | E16: Cuenca Neuquina & Vaca Muerta | F16: Operations & Engineering | G16: Operations Services | H16: Neuquén - EFiS | I16: Macias Ceferino Oscar | J16: =VLOOKUP(B16,#REF!,13,0) -> #REF!
A17: 1 | B17: 3392846 | C17: Vacante - Integrity Supervisor | D17: EFR-FN0931 | E17: Cuenca Neuquina & Vaca Muerta | F17: Operations & Engineering | G17: Maintenance | H17: Neuquén - EFiS | I17: Diaz Luis Alberto | J17: =VLOOKUP(B17,#REF!,13,0) -> #REF!
A18: 1 | B18: 3401242 | C18: Vacante - Maintenance Sr. Supervisor | D18: EFR-FN0900 | E18: Cuenca Neuquina & Vaca Muerta | F18: Operations & Engineering | G18: Maintenance | H18: Neuquén - EFiS | I18: Mazoue Juan Manuel | J18: =VLOOKUP(B18,#REF!,13,0) -> #REF!
